[
  {
    "image": "https://assets.myntassets.com/dpr_2,q_60,w_210,c_limit,fl_progressive/assets/images/12787316/2023/4/4/1f253fbd-ccbe-4549-a59c-ed41207422e81680609459106-HERENOW-Men-Multicoloured-Printed-Round-Neck-T-shirt-1781680-1.jpg",
    "brand": "HERE&NOW",
    "color": "Multy",
    "title": "Men Printed Round Neck T-shirt",
    "size": ["XS", "S", "2XL", "3XL"],
    "sellingPrice": 269,
    "marketPrice": 899,
    "percentageDiscount": 70,
    "faltDiscount": "",
    "inventory": 10,
    "collections": "Men",
    "subCollection": "Topwear",
    "gender": "Men",
    "category": "T-Shirts"
  },
  {
    "image": "https://assets.myntassets.com/dpr_2,q_60,w_210,c_limit,fl_progressive/assets/images/19446606/2022/8/9/f53fe7e8-affa-4bfb-9f35-4d2c33de12aa1660043675628Tshirts1.jpg",
    "brand": "VEIRDO",
    "color": "Multy",
    "title": "Men Printed Oversize T-shirt",
    "size": ["XS", "S", "M", "L"],
    "sellingPrice": 599,
    "marketPrice": 1199,
    "percentageDiscount": 50,
    "faltDiscount": "",
    "inventory": 10,
    "collections": "Men",
    "subCollection": "Topwear",
    "gender": "Men",
    "category": "T-Shirts"
  },
  {
    "image": "https://assets.myntassets.com/dpr_2,q_60,w_210,c_limit,fl_progressive/assets/images/18277922/2022/5/16/1f46c502-5c98-4e8b-9b1f-fb3074671f971652677937549VEIRDOMenMulticolouredMickeyMousePrintedV-NeckExtendedSleeve1.jpg",
    "brand": "VEIRDO",
    "color": "Multy",
    "title": "Men Mickey Oversize T-shirt",
    "size": ["XS", "S", "XL", "2XL"],
    "sellingPrice": 599,
    "marketPrice": 1199,
    "percentageDiscount": 50,
    "faltDiscount": "",
    "inventory": 10,
    "collections": "Men",
    "subCollection": "Topwear",
    "gender": "Men",
    "category": "T-Shirts"
  },
  {
    "image": "https://assets.myntassets.com/dpr_2,q_60,w_210,c_limit,fl_progressive/assets/images/21665258/2023/2/7/e5a38bd4-5a4f-4bae-8053-638741c442891675750987900-Kook-N-Keech-Men-Tshirts-5931675750987396-1.jpg",
    "brand": "Kook N Keech",
    "color": "Multy",
    "title": "Men Tie and Dye Printed Loose T-shirt",
    "size": ["XS", "M", "2XL", "3XL"],
    "sellingPrice": 599,
    "marketPrice": 999,
    "percentageDiscount": 40,
    "faltDiscount": "",
    "inventory": 10,
    "collections": "Men",
    "subCollection": "Topwear",
    "gender": "Men",
    "category": "T-Shirts"
  },
  {
    "image": "https://assets.myntassets.com/dpr_2,q_60,w_210,c_limit,fl_progressive/assets/images/17728638/2022/4/1/ddbcc7a4-f7c8-4420-8f47-1a8a75b820ff1648817928328TheSouledStoreMenMulticolouredPrintedAppliqueLooseT-shirt1.jpg",
    "brand": "The Souled Store",
    "color": "Multy",
    "title": "Oversized T-Shirt",
    "size": ["S", "L", "XL", "2XL"],
    "sellingPrice": 996,
    "marketPrice": 1499,
    "percentageDiscount": "",
    "faltDiscount": 503,
    "inventory": 10,
    "collections": "Men",
    "subCollection": "Topwear",
    "gender": "Men",
    "category": "T-Shirts"
  },
  {
    "image": "https://assets.myntassets.com/dpr_2,q_60,w_210,c_limit,fl_progressive/assets/images/2232166/2018/3/24/11521879152175-Mast--Harbour-Men-Tshirts-4821521879152063-1.jpg",
    "brand": "Mast & Harbour",
    "color": "Multy",
    "title": "Colourblocked Round Neck T-shirt",
    "size": ["XS", "L", "2XL", "3XL"],
    "sellingPrice": 239,
    "marketPrice": 799,
    "percentageDiscount": 70,
    "faltDiscount": "",
    "inventory": 10,
    "collections": "Men",
    "subCollection": "Topwear",
    "gender": "Men",
    "category": "T-Shirts"
  },
  {
    "image": "https://assets.myntassets.com/dpr_2,q_60,w_210,c_limit,fl_progressive/assets/images/16569442/2021/12/21/b5b1be5b-1fd6-453e-84ef-8cf19042b39d1640071917222plusSMenMulticolouredStripedPoloCollarPocketsT-shirt1.jpg",
    "brand": "plusS",
    "color": "Multy",
    "title": "Striped Polo Collar T-shirt",
    "size": ["S", "M", "XL", "3XL"],
    "sellingPrice": 594,
    "marketPrice": 1980,
    "percentageDiscount": 70,
    "faltDiscount": "",
    "inventory": 10,
    "collections": "Men",
    "subCollection": "Topwear",
    "gender": "Men",
    "category": "T-Shirts"
  },
  {
    "image": "https://assets.myntassets.com/dpr_2,q_60,w_210,c_limit,fl_progressive/assets/images/8458523/2019/8/22/25854440-74a4-4cde-825c-9260a38264491566464635986-ether-Men-Tshirts-1181566464634829-1.jpg",
    "brand": "ether",
    "color": "Multy",
    "title": "Men Polo Collar Pure Cotton T-shirt",
    "size": ["XS", "S", "M", "L"],
    "sellingPrice": 584,
    "marketPrice": 1299,
    "percentageDiscount": 55,
    "faltDiscount": "",
    "inventory": 10,
    "collections": "Men",
    "subCollection": "Topwear",
    "gender": "Men",
    "category": "T-Shirts"
  },
  {
    "image": "https://assets.myntassets.com/dpr_2,q_60,w_210,c_limit,fl_progressive/assets/images/19856576/2022/9/8/4755ca9d-3abe-4d77-abce-e3440fe47ffd1662638153252TheSouledStoreMenMulticolouredTypographyAppliqueLooseT-shirt1.jpg",
    "brand": "The Souled Store",
    "color": "Multy",
    "title": "Oversized T-Shirt",
    "size": ["S", "XL", "2XL", "3XL"],
    "sellingPrice": 944,
    "marketPrice": 1499,
    "percentageDiscount": "",
    "faltDiscount": 555,
    "inventory": 10,
    "collections": "Men",
    "subCollection": "Topwear",
    "gender": "Men",
    "category": "T-Shirts"
  },
  {
    "image": "https://assets.myntassets.com/dpr_2,q_60,w_210,c_limit,fl_progressive/assets/images/16696330/2022/1/5/848fe088-ca2e-463e-9a05-2d06924762b31641387645942PepeJeansMenMulticolouredColourblockedExtendedSleevesAppliqu1.jpg",
    "brand": "Pepe Jeans",
    "color": "Multy",
    "title": "Men Colourblocked Slim Fit T-shirt",
    "size": ["XS", "M", "L", "3XL"],
    "sellingPrice": 824,
    "marketPrice": 1499,
    "percentageDiscount": 45,
    "faltDiscount": "",
    "inventory": 10,
    "collections": "Men",
    "subCollection": "Topwear",
    "gender": "Men",
    "category": "T-Shirts"
  },
  {
    "image": "https://assets.myntassets.com/dpr_2,q_60,w_210,c_limit,fl_progressive/assets/images/15610024/2021/11/18/73f4c869-5063-42ad-991a-13b045f3e8ee1637229138124-HERENOW-Men-Tshirts-3041637229137468-1.jpg",
    "brand": "HERE&NOW",
    "color": "Multy",
    "title": "Men Striped Cotton T-shirt",
    "size": ["S", "L", "XL", "2XL"],
    "sellingPrice": 406,
    "marketPrice": 1099,
    "percentageDiscount": 63,
    "faltDiscount": "",
    "inventory": 10,
    "collections": "Men",
    "subCollection": "Topwear",
    "gender": "Men",
    "category": "T-Shirts"
  },
  {
    "image": "https://assets.myntassets.com/dpr_2,q_60,w_210,c_limit,fl_progressive/assets/images/21881838/2023/2/9/22316489-6087-4f4a-9cc3-8888d3219ff11675925333671RegularFitT-shirt1.jpg",
    "brand": "H&M",
    "color": "Multy",
    "title": "Regular Fit T-shirt",
    "size": ["M", "L", "2XL", "3XL"],
    "sellingPrice": 0,
    "marketPrice": 0,
    "percentageDiscount": "",
    "faltDiscount": "",
    "inventory": 10,
    "collections": "Men",
    "subCollection": "Topwear",
    "gender": "Men",
    "category": "T-Shirts"
  },
  {
    "image": "https://assets.myntassets.com/dpr_2,q_60,w_210,c_limit,fl_progressive/assets/images/15830252/2021/10/16/e835cc7c-f6a5-4bc7-9541-ef8841d18afc1634388313453LOCOMOTIVEMenMulticolouredPrintedPocketsSlimFitT-shirt1.jpg",
    "brand": "LOCOMOTIVE",
    "color": "Multy",
    "title": "Men Printed Pockets Slim Fit T-shirt",
    "size": ["M", "L", "XL", "3XL"],
    "sellingPrice": 284,
    "marketPrice": 949,
    "percentageDiscount": 70,
    "faltDiscount": "",
    "inventory": 10,
    "collections": "Men",
    "subCollection": "Topwear",
    "gender": "Men",
    "category": "T-Shirts"
  },
  {
    "image": "https://assets.myntassets.com/dpr_2,q_60,w_210,c_limit,fl_progressive/assets/images/17056966/2022/2/4/720a5c7e-9c2e-4640-a6d9-2f32a9ac506a1643987388700PepeJeansMenMulticolouredPrintedPocketsSlimFitT-shirt1.jpg",
    "brand": "Pepe Jeans",
    "color": "Multy",
    "title": "Men Printed Slim Fit T-shirt",
    "size": ["XS", "M", "L", "3XL"],
    "sellingPrice": 879,
    "marketPrice": 1599,
    "percentageDiscount": 45,
    "faltDiscount": "",
    "inventory": 10,
    "collections": "Men",
    "subCollection": "Topwear",
    "gender": "Men",
    "category": "T-Shirts"
  },
  {
    "image": "https://assets.myntassets.com/dpr_2,q_60,w_210,c_limit,fl_progressive/assets/images/15058716/2022/9/7/ed9cf2d0-67b9-4c38-b9f3-c67f9d0d45291662550927602MastHarbourMenMulticolouredColourblockedPureCottonT-shirt1.jpg",
    "brand": "Mast & Harbour",
    "color": "Multy",
    "title": "Men Colourblocked T-shirt",
    "size": ["XS", "M", "L", "XL"],
    "sellingPrice": 269,
    "marketPrice": 899,
    "percentageDiscount": 70,
    "faltDiscount": "",
    "inventory": 10,
    "collections": "Men",
    "subCollection": "Topwear",
    "gender": "Men",
    "category": "T-Shirts"
  },
  {
    "image": "https://assets.myntassets.com/dpr_2,q_60,w_210,c_limit,fl_progressive/assets/images/17346436/2022/3/2/fd25dc1f-d869-456b-befa-72d1f0fb56e01646207741801PepeJeansMenMulticolouredStripedPoloCollarT-shirt1.jpg",
    "brand": "Pepe Jeans",
    "color": "Multy",
    "title": "Men Polo Collar T-shirt",
    "size": ["XS", "L", "XL", "3XL"],
    "sellingPrice": 1099,
    "marketPrice": 1999,
    "percentageDiscount": 45,
    "faltDiscount": "",
    "inventory": 10,
    "collections": "Men",
    "subCollection": "Topwear",
    "gender": "Men",
    "category": "T-Shirts"
  },
  {
    "image": "https://assets.myntassets.com/dpr_2,q_60,w_210,c_limit,fl_progressive/assets/images/16607682/2022/4/20/301be5c8-52c6-4bc2-9ca5-06e2f3e1b20a1650456498056CampusSutraMenMulticolouredStripedPoloCollarPocketsOutdoorT-1.jpg",
    "brand": "Campus Sutra",
    "color": "Multy",
    "title": "Men Striped Polo Collar Pockets T-shirt",
    "size": ["XS", "M", "L", "XL"],
    "sellingPrice": 683,
    "marketPrice": 1199,
    "percentageDiscount": 43,
    "faltDiscount": "",
    "inventory": 10,
    "collections": "Men",
    "subCollection": "Topwear",
    "gender": "Men",
    "category": "T-Shirts"
  },
  {
    "image": "https://assets.myntassets.com/dpr_2,q_60,w_210,c_limit,fl_progressive/assets/images/17571486/2022/9/27/f1f9fffd-c0b7-48ce-9596-cf87f0566c0b1664262800652-Mast--Harbour-Men-Tshirts-141664262800260-1.jpg",
    "brand": "Mast & Harbour",
    "color": "Multy",
    "title": "Men Striped Polo Collar T-shirt",
    "size": ["M", "L", "XL", "2XL"],
    "sellingPrice": 0,
    "marketPrice": 0,
    "percentageDiscount": "",
    "faltDiscount": "",
    "inventory": 10,
    "collections": "Men",
    "subCollection": "Topwear",
    "gender": "Men",
    "category": "T-Shirts"
  },
  {
    "image": "https://assets.myntassets.com/dpr_2,q_60,w_210,c_limit,fl_progressive/assets/images/17895078/2022/7/22/a63d847b-1bde-4167-af83-46c0906c05881658484622792-U-S-Polo-Assn-Men-Multicoloured-Colourblocked-Casual-T-shirt-1.jpg",
    "brand": "U.S. Polo Assn.",
    "color": "Multy",
    "title": "Men Colourblocked T-shirt",
    "size": ["S", "M", "L", "2XL"],
    "sellingPrice": 575,
    "marketPrice": 1199,
    "percentageDiscount": 52,
    "faltDiscount": "",
    "inventory": 10,
    "collections": "Men",
    "subCollection": "Topwear",
    "gender": "Men",
    "category": "T-Shirts"
  },
  {
    "image": "https://assets.myntassets.com/dpr_2,q_60,w_210,c_limit,fl_progressive/assets/images/16971940/2022/3/24/f6c30cbf-8933-4a33-bc00-0beecefef0e61648121833408-Theo-Splatter-Print-T-Shirt-9091648121832916-1.jpg",
    "brand": "BEAT LONDON by PEPE JEANS",
    "color": "Multy",
    "title": "Men Printed Slim Fit T-shirt",
    "size": ["XS", "M", "XL", "2XL"],
    "sellingPrice": 479,
    "marketPrice": 1199,
    "percentageDiscount": 60,
    "faltDiscount": "",
    "inventory": 10,
    "collections": "Men",
    "subCollection": "Topwear",
    "gender": "Men",
    "category": "T-Shirts"
  },
  {
    "image": "https://assets.myntassets.com/dpr_2,q_60,w_210,c_limit,fl_progressive/assets/images/14413270/2021/9/21/418928b5-0502-4a84-b093-1933f9bc18c11632206341318-abof-Men-Tshirts-8011632206340678-1.jpg",
    "brand": "abof",
    "color": "Multy",
    "title": "Men Striped Polo Collar T-shirt",
    "size": ["XS", "M", "L", "3XL"],
    "sellingPrice": 419,
    "marketPrice": 1399,
    "percentageDiscount": 70,
    "faltDiscount": "",
    "inventory": 10,
    "collections": "Men",
    "subCollection": "Topwear",
    "gender": "Men",
    "category": "T-Shirts"
  },
  {
    "image": "https://assets.myntassets.com/dpr_2,q_60,w_210,c_limit,fl_progressive/assets/images/22235800/2023/3/6/4d18f46e-a986-4848-aacb-40917280e1981678072990571RelaxedFitPrintedT-shirt1.jpg",
    "brand": "H&M",
    "color": "Multy",
    "title": "Relaxed Fit Printed T-shirt",
    "size": ["S", "M", "XL", "3XL"],
    "sellingPrice": 0,
    "marketPrice": 0,
    "percentageDiscount": "",
    "faltDiscount": "",
    "inventory": 10,
    "collections": "Men",
    "subCollection": "Topwear",
    "gender": "Men",
    "category": "T-Shirts"
  },
  {
    "image": "https://assets.myntassets.com/dpr_2,q_60,w_210,c_limit,fl_progressive/assets/images/22235782/2023/3/6/64314197-7185-4ba9-8771-efd3710054011678072973312RelaxedFitPrintedT-shirt1.jpg",
    "brand": "H&M",
    "color": "Multy",
    "title": "Relaxed Fit Printed T-shirt",
    "size": ["XS", "M", "L", "2XL"],
    "sellingPrice": 0,
    "marketPrice": 0,
    "percentageDiscount": "",
    "faltDiscount": "",
    "inventory": 10,
    "collections": "Men",
    "subCollection": "Topwear",
    "gender": "Men",
    "category": "T-Shirts"
  },
  {
    "image": "https://assets.myntassets.com/dpr_2,q_60,w_210,c_limit,fl_progressive/assets/images/20461274/2022/10/19/46c2484d-6211-4af4-ac27-4f67027dcb181666178660928LouisPhilippeMulticolouredT-shirt1.jpg",
    "brand": "Louis Philippe Sport",
    "color": "Multy",
    "title": "Men Striped Polo Collar T-shirt",
    "size": ["XS", "S", "XL", "2XL"],
    "sellingPrice": 0,
    "marketPrice": 0,
    "percentageDiscount": "",
    "faltDiscount": "",
    "inventory": 10,
    "collections": "Men",
    "subCollection": "Topwear",
    "gender": "Men",
    "category": "T-Shirts"
  },
  {
    "image": "https://assets.myntassets.com/dpr_2,q_60,w_210,c_limit,fl_progressive/assets/images/21167944/2022/12/12/3c67b53e-5741-46be-b619-8e7d5c8a503b1670859217150Tshirts5.jpg",
    "brand": "The Souled Store",
    "color": "Multy",
    "title": "Typography Cotton T-shirt",
    "size": ["XS", "L", "2XL", "3XL"],
    "sellingPrice": 1343,
    "marketPrice": 1699,
    "percentageDiscount": "",
    "faltDiscount": 356,
    "inventory": 10,
    "collections": "Men",
    "subCollection": "Topwear",
    "gender": "Men",
    "category": "T-Shirts"
  },
  {
    "image": "https://assets.myntassets.com/dpr_2,q_60,w_210,c_limit,fl_progressive/assets/images/20739970/2022/11/14/1d717c68-98bf-4c0b-bbfa-0c204a2159f41668412461643FrontTextDetailColorblockOversizedT-shirt1.jpg",
    "brand": "Styli",
    "color": "Multy",
    "title": "Oversized Colorblocked T-shirt",
    "size": ["XS", "S", "L", "2XL"],
    "sellingPrice": 494,
    "marketPrice": 549,
    "percentageDiscount": 10,
    "faltDiscount": "",
    "inventory": 10,
    "collections": "Men",
    "subCollection": "Topwear",
    "gender": "Men",
    "category": "T-Shirts"
  },
  {
    "image": "https://assets.myntassets.com/dpr_2,q_60,w_210,c_limit,fl_progressive/assets/images/productimage/2021/3/18/34b4d985-25b9-4cae-997d-cb5685769ddd1616048394994-1.jpg",
    "brand": "LOCOMOTIVE",
    "color": "Multy",
    "title": "Colourblocked Round Neck T-shirt",
    "size": ["XS", "M", "L", "2XL"],
    "sellingPrice": 292,
    "marketPrice": 749,
    "percentageDiscount": 61,
    "faltDiscount": "",
    "inventory": 10,
    "collections": "Men",
    "subCollection": "Topwear",
    "gender": "Men",
    "category": "T-Shirts"
  },
  {
    "image": "https://assets.myntassets.com/dpr_2,q_60,w_210,c_limit,fl_progressive/assets/images/17766976/2022/4/5/1f7e8665-9cf7-4af8-9cca-3b61ffaea7a21649165153092DukeMenMulticoloured3V-NeckSlimFitT-shirt1.jpg",
    "brand": "Duke",
    "color": "Multy",
    "title": "Pack Of 3 Slim Fit T-shirts",
    "size": ["M", "L", "2XL", "3XL"],
    "sellingPrice": 959,
    "marketPrice": 1199,
    "percentageDiscount": 20,
    "faltDiscount": "",
    "inventory": 10,
    "collections": "Men",
    "subCollection": "Topwear",
    "gender": "Men",
    "category": "T-Shirts"
  },
  {
    "image": "https://assets.myntassets.com/dpr_2,q_60,w_210,c_limit,fl_progressive/assets/images/17571478/2022/11/23/b5675752-0e8d-4cbb-a09e-398535ed420f1669205698324-Mast--Harbour-Men-Tshirts-9531669205697845-1.jpg",
    "brand": "Mast & Harbour",
    "color": "Multy",
    "title": "Men Pure Cotton Polo T-Shirt",
    "size": ["S", "L", "XL", "2XL"],
    "sellingPrice": 0,
    "marketPrice": 0,
    "percentageDiscount": "",
    "faltDiscount": "",
    "inventory": 10,
    "collections": "Men",
    "subCollection": "Topwear",
    "gender": "Men",
    "category": "T-Shirts"
  },
  {
    "image": "https://assets.myntassets.com/dpr_2,q_60,w_210,c_limit,fl_progressive/assets/images/20344234/2022/10/10/091f81bd-544a-4283-abdb-d8e45f6d8bab1665394129442VanHeusenMulticolouredTShirt1.jpg",
    "brand": "Van Heusen Flex",
    "color": "Multy",
    "title": "Men Polo Collar T-shirt",
    "size": ["XS", "L", "XL", "3XL"],
    "sellingPrice": 949,
    "marketPrice": 1899,
    "percentageDiscount": 50,
    "faltDiscount": "",
    "inventory": 10,
    "collections": "Men",
    "subCollection": "Topwear",
    "gender": "Men",
    "category": "T-Shirts"
  },
  {
    "image": "https://assets.myntassets.com/dpr_2,q_60,w_210,c_limit,fl_progressive/assets/images/19889468/2022/9/30/3c2b8b68-05d4-4bb9-a503-fb0c2daffcf21664528013915-FOREVER-21-Men-Multicoloured-Graphic-Printed-Pure-Cotton-T-s-1.jpg",
    "brand": "FOREVER 21",
    "color": "Multy",
    "title": "Men Pure Cotton Casual T-shirt",
    "size": ["S", "M", "XL", "2XL"],
    "sellingPrice": 659,
    "marketPrice": 1099,
    "percentageDiscount": 40,
    "faltDiscount": "",
    "inventory": 10,
    "collections": "Men",
    "subCollection": "Topwear",
    "gender": "Men",
    "category": "T-Shirts"
  },
  {
    "image": "https://assets.myntassets.com/dpr_2,q_60,w_210,c_limit,fl_progressive/assets/images/17411458/2022/3/7/79d7a9ad-eb0b-4d28-b511-d0ce224313d01646629518362USPoloAssnMenMulticolouredColourblockedPoloCollarAppliqueT-s1.jpg",
    "brand": "U.S. Polo Assn.",
    "color": "Multy",
    "title": "Men Colourblocked Polo T-shirt",
    "size": ["XS", "S", "XL", "3XL"],
    "sellingPrice": 999,
    "marketPrice": 1999,
    "percentageDiscount": 50,
    "faltDiscount": "",
    "inventory": 10,
    "collections": "Men",
    "subCollection": "Topwear",
    "gender": "Men",
    "category": "T-Shirts"
  },
  {
    "image": "https://assets.myntassets.com/dpr_2,q_60,w_210,c_limit,fl_progressive/assets/images/15932436/2021/10/26/65f51e2f-f04a-422e-8cc7-62de3d4972691635250005176Tshirts1.jpg",
    "brand": "FERANOID",
    "color": "Multy",
    "title": "Men Pack Of 3 T-shirts",
    "size": ["XS", "S", "M", "3XL"],
    "sellingPrice": 1220,
    "marketPrice": 3299,
    "percentageDiscount": 63,
    "faltDiscount": "",
    "inventory": 10,
    "collections": "Men",
    "subCollection": "Topwear",
    "gender": "Men",
    "category": "T-Shirts"
  },
  {
    "image": "https://assets.myntassets.com/dpr_2,q_60,w_210,c_limit,fl_progressive/assets/images/15162494/2021/8/17/d39171fc-abec-4f7e-81a0-f54805d566441629186377576EnnobleMenMulticolouredPrintedRawEdgeT-shirt1.jpg",
    "brand": "Ennoble",
    "color": "Multy",
    "title": "Men Tie  Dyed Cotton Pure Cotton T-shirt",
    "size": ["XS", "M", "L", "2XL"],
    "sellingPrice": 1538,
    "marketPrice": 2699,
    "percentageDiscount": 43,
    "faltDiscount": "",
    "inventory": 10,
    "collections": "Men",
    "subCollection": "Topwear",
    "gender": "Men",
    "category": "T-Shirts"
  },
  {
    "image": "https://assets.myntassets.com/dpr_2,q_60,w_210,c_limit,fl_progressive/assets/images/21679244/2023/1/23/ac2d2831-ef22-4c67-bef6-e8b4f006a0c01674491906166TheSouledStoreMenMulticolouredPrintedRawEdgeLooseT-shirt5.jpg",
    "brand": "The Souled Store",
    "color": "Multy",
    "title": "Oversized T-Shirt",
    "size": ["XS", "M", "L", "3XL"],
    "sellingPrice": 996,
    "marketPrice": 999,
    "percentageDiscount": "",
    "faltDiscount": 3,
    "inventory": 10,
    "collections": "Men",
    "subCollection": "Topwear",
    "gender": "Men",
    "category": "T-Shirts"
  },
  {
    "image": "https://assets.myntassets.com/dpr_2,q_60,w_210,c_limit,fl_progressive/assets/images/16705634/2022/1/6/a677bf59-1252-4c09-82f6-6222451a0ca31641464916896DollarMenMulticolouredTypography5PrintedAppliqueT-shirt1.jpg",
    "brand": "Dollar",
    "color": "Multy",
    "title": "Set Of 5 Men T-shirt",
    "size": ["XS", "S", "L", "XL"],
    "sellingPrice": 1179,
    "marketPrice": 2145,
    "percentageDiscount": 45,
    "faltDiscount": "",
    "inventory": 10,
    "collections": "Men",
    "subCollection": "Topwear",
    "gender": "Men",
    "category": "T-Shirts"
  },
  {
    "image": "https://assets.myntassets.com/dpr_2,q_60,w_210,c_limit,fl_progressive/assets/images/17520750/2022/3/24/bb39d413-91fb-4a9e-bcc5-07d2740409561648098382561-Peter-England-Casuals-Men-Tshirts-5731648098382074-1.jpg",
    "brand": "Peter England Casuals",
    "color": "Multy",
    "title": "Snug Floral Printed T-shirt",
    "size": ["S", "M", "L", "2XL"],
    "sellingPrice": 699,
    "marketPrice": 1399,
    "percentageDiscount": 50,
    "faltDiscount": "",
    "inventory": 10,
    "collections": "Men",
    "subCollection": "Topwear",
    "gender": "Men",
    "category": "T-Shirts"
  },
  {
    "image": "https://assets.myntassets.com/dpr_2,q_60,w_210,c_limit,fl_progressive/assets/images/21702174/2023/1/25/801ea4e6-36f3-4af0-815f-c0d290e87d871674635182366G-92Sector63NoidaUttarPradesh-2013011.jpg",
    "brand": "bigbanana",
    "color": "Multy",
    "title": "Men Bio Finish Henley Neck Raw Edge T-shirt",
    "size": ["M", "XL", "2XL", "3XL"],
    "sellingPrice": 949,
    "marketPrice": 1899,
    "percentageDiscount": 50,
    "faltDiscount": "",
    "inventory": 10,
    "collections": "Men",
    "subCollection": "Topwear",
    "gender": "Men",
    "category": "T-Shirts"
  },
  {
    "image": "https://assets.myntassets.com/dpr_2,q_60,w_210,c_limit,fl_progressive/assets/images/18353940/2022/5/20/19a1f0d0-8c59-4f3f-9d9f-8d61022d06461653047440953VanHeusenSportMenMulticolouredStripedT-shirt1.jpg",
    "brand": "Van Heusen Sport",
    "color": "Multy",
    "title": "Men Striped T-shirt",
    "size": ["XS", "M", "L", "2XL"],
    "sellingPrice": 549,
    "marketPrice": 1099,
    "percentageDiscount": 50,
    "faltDiscount": "",
    "inventory": 10,
    "collections": "Men",
    "subCollection": "Topwear",
    "gender": "Men",
    "category": "T-Shirts"
  },
  {
    "image": "https://assets.myntassets.com/dpr_2,q_60,w_210,c_limit,fl_progressive/assets/images/17098456/2022/2/9/1014e7f9-9768-40ea-a442-789c2222339a1644386739414WoodlandMenMulticolouredPrintedV-NeckPocketsT-shirt1.jpg",
    "brand": "Woodland",
    "color": "Multy",
    "title": "Men Printed T-shirt",
    "size": ["XS", "L", "XL", "2XL"],
    "sellingPrice": 1247,
    "marketPrice": 2495,
    "percentageDiscount": 50,
    "faltDiscount": "",
    "inventory": 10,
    "collections": "Men",
    "subCollection": "Topwear",
    "gender": "Men",
    "category": "T-Shirts"
  },
  {
    "image": "https://assets.myntassets.com/dpr_2,q_60,w_210,c_limit,fl_progressive/assets/images/17098466/2022/2/9/657847e4-04ed-4e90-ada1-4b8f7f1ebbaa1644386655045WoodlandMenMulticolouredCamouflagePrintedTropicalPocketsT-sh1.jpg",
    "brand": "Woodland",
    "color": "Multy",
    "title": "Men Camouflage Printed Polo Collar T-shirt",
    "size": ["XS", "S", "L", "2XL"],
    "sellingPrice": 1247,
    "marketPrice": 2495,
    "percentageDiscount": 50,
    "faltDiscount": "",
    "inventory": 10,
    "collections": "Men",
    "subCollection": "Topwear",
    "gender": "Men",
    "category": "T-Shirts"
  },
  {
    "image": "https://assets.myntassets.com/dpr_2,q_60,w_210,c_limit,fl_progressive/assets/images/18766782/2022/6/17/d25b05d6-665d-421a-a7d3-dba98eae14881655475691414VanHeusenMulticolouredTShirt1.jpg",
    "brand": "Van Heusen Sport",
    "color": "Multy",
    "title": "Men Striped Polo Collar Applique T-shirt",
    "size": ["S", "L", "XL", "2XL"],
    "sellingPrice": 1699,
    "marketPrice": 1999,
    "percentageDiscount": 15,
    "faltDiscount": "",
    "inventory": 10,
    "collections": "Men",
    "subCollection": "Topwear",
    "gender": "Men",
    "category": "T-Shirts"
  },
  {
    "image": "https://assets.myntassets.com/dpr_2,q_60,w_210,c_limit,fl_progressive/assets/images/21689396/2023/1/24/bf05bfbf-d3fe-4022-b689-671051a2e74b1674570143062Tshirts1.jpg",
    "brand": "PEPLOS",
    "color": "Multy",
    "title": "Men Striped Polo Neck T-shirt",
    "size": ["M", "L", "XL", "2XL"],
    "sellingPrice": 839,
    "marketPrice": 1199,
    "percentageDiscount": 30,
    "faltDiscount": "",
    "inventory": 10,
    "collections": "Men",
    "subCollection": "Topwear",
    "gender": "Men",
    "category": "T-Shirts"
  },
  {
    "image": "https://assets.myntassets.com/dpr_2,q_60,w_210,c_limit,fl_progressive/assets/images/20786692/2022/11/17/f87fd349-6aeb-4680-915a-01dd58179d8f1668668498801MensGymActiveweart-shirt1.jpg",
    "brand": "Tistabene",
    "color": "Multy",
    "title": "Men Printed T-shirt",
    "size": ["XS", "M", "XL", "3XL"],
    "sellingPrice": 240,
    "marketPrice": 649,
    "percentageDiscount": 63,
    "faltDiscount": "",
    "inventory": 10,
    "collections": "Men",
    "subCollection": "Topwear",
    "gender": "Men",
    "category": "T-Shirts"
  },
  {
    "image": "https://assets.myntassets.com/dpr_2,q_60,w_210,c_limit,fl_progressive/assets/images/15637268/2021/9/27/17b6afb7-174e-445f-ab8c-9ca10c3bb7ca1632736871815FIDODIDOMenWhite3PrintedAppliqueSlimFitT-shirt1.jpg",
    "brand": "FIDO DIDO",
    "color": "Multy",
    "title": "PackOf3 Printed SlimFitT-shirt",
    "size": ["S", "L", "2XL", "3XL"],
    "sellingPrice": 749,
    "marketPrice": 2999,
    "percentageDiscount": 75,
    "faltDiscount": "",
    "inventory": 10,
    "collections": "Men",
    "subCollection": "Topwear",
    "gender": "Men",
    "category": "T-Shirts"
  },
  {
    "image": "https://assets.myntassets.com/dpr_2,q_60,w_210,c_limit,fl_progressive/assets/images/18913092/2022/6/29/3be5b97c-7bf2-4ae8-97c5-4e02dda2ae701656523371016Tshirts1.jpg",
    "brand": "Rodamo",
    "color": "Multy",
    "title": "Men Striped Polo Collar Slim Fit T-shirt",
    "size": ["XS", "S", "M", "3XL"],
    "sellingPrice": 744,
    "marketPrice": 1049,
    "percentageDiscount": 29,
    "faltDiscount": "",
    "inventory": 10,
    "collections": "Men",
    "subCollection": "Topwear",
    "gender": "Men",
    "category": "T-Shirts"
  },
  {
    "image": "https://assets.myntassets.com/dpr_2,q_60,w_210,c_limit,fl_progressive/assets/images/21411080/2023/1/4/003b6fa6-5d23-4f2b-a565-f34253ac27781672831314479MenMultiStripeCrewNeckRoundNeckT-Shirts1.jpg",
    "brand": "Peter England Casuals",
    "color": "Multy",
    "title": "Men Striped Slim Fit T-shirt",
    "size": ["S", "L", "2XL", "3XL"],
    "sellingPrice": 699,
    "marketPrice": 999,
    "percentageDiscount": 30,
    "faltDiscount": "",
    "inventory": 10,
    "collections": "Men",
    "subCollection": "Topwear",
    "gender": "Men",
    "category": "T-Shirts"
  },
  {
    "image": "https://assets.myntassets.com/dpr_2,q_60,w_210,c_limit,fl_progressive/assets/images/20461294/2022/10/19/90e03f00-0bb3-4cad-89a9-c1521aba5f8e1666175725463LouisPhilippeMulticolouredT-shirt1.jpg",
    "brand": "Louis Philippe Sport",
    "color": "Multy",
    "title": "Men Striped Polo Collar T-shirt",
    "size": ["S", "M", "L", "3XL"],
    "sellingPrice": 0,
    "marketPrice": 0,
    "percentageDiscount": "",
    "faltDiscount": "",
    "inventory": 10,
    "collections": "Men",
    "subCollection": "Topwear",
    "gender": "Men",
    "category": "T-Shirts"
  },
  {
    "image": "https://assets.myntassets.com/dpr_2,q_60,w_210,c_limit,fl_progressive/assets/images/2417178/2018/1/22/11516604806321-Wear-Your-Mind-Multicolor-Polyester-Vest-For-Men-9351516604806194-1.jpg",
    "brand": "Wear Your Mind",
    "color": "Multy",
    "title": "Printed Round Neck T-shirt",
    "size": ["XS", "M", "L", "XL"],
    "sellingPrice": 349,
    "marketPrice": 999,
    "percentageDiscount": 65,
    "faltDiscount": "",
    "inventory": 10,
    "collections": "Men",
    "subCollection": "Topwear",
    "gender": "Men",
    "category": "T-Shirts"
  },
  {
    "image": "https://assets.myntassets.com/dpr_2,q_60,w_210,c_limit,fl_progressive/assets/images/20387474/2022/10/13/03e04903-4c85-44e5-843e-7861a43da5a01665668684284Tshirts1.jpg",
    "brand": "Classic Polo",
    "color": "Multy",
    "title": "Polo Collar Slim Fit T-shirt",
    "size": ["XS", "S", "L", "XL"],
    "sellingPrice": 0,
    "marketPrice": 0,
    "percentageDiscount": "",
    "faltDiscount": "",
    "inventory": 10,
    "collections": "Men",
    "subCollection": "Topwear",
    "gender": "Men",
    "category": "T-Shirts"
  },
  {
    "image": "https://assets.myntassets.com/dpr_2,q_60,w_210,c_limit,fl_progressive/assets/images/20387474/2022/10/13/03e04903-4c85-44e5-843e-7861a43da5a01665668684284Tshirts1.jpg",
    "brand": "Classic Polo",
    "color": "Multy",
    "title": "Polo Collar Slim Fit T-shirt",
    "size": ["XS", "S", "M", "3XL"],
    "sellingPrice": 0,
    "marketPrice": 0,
    "percentageDiscount": "",
    "faltDiscount": "",
    "inventory": 10,
    "collections": "Men",
    "subCollection": "Topwear",
    "gender": "Men",
    "category": "T-Shirts"
  },
  {
    "image": "https://assets.myntassets.com/dpr_2,q_60,w_210,c_limit,fl_progressive/assets/images/18732818/2022/6/14/64495ac9-e729-4b0f-9cec-66cde894a0501655216471378LouisPhilippeMulticolouredT-shirt1.jpg",
    "brand": "Louis Philippe Jeans",
    "color": "Multy",
    "title": "Men Striped Slim Fit T-shirt",
    "size": ["XS", "XL", "2XL", "3XL"],
    "sellingPrice": 1189,
    "marketPrice": 1399,
    "percentageDiscount": 15,
    "faltDiscount": "",
    "inventory": 10,
    "collections": "Men",
    "subCollection": "Topwear",
    "gender": "Men",
    "category": "T-Shirts"
  },
  {
    "image": "https://assets.myntassets.com/dpr_2,q_60,w_210,c_limit,fl_progressive/assets/images/18888336/2022/6/28/bc5601f2-d5b4-4f1a-93ec-797ce278b7bd1656421443092Tshirts1.jpg",
    "brand": "Jack & Jones",
    "color": "Multy",
    "title": "Men Printed Polo Collar Applique T-shirt",
    "size": ["XS", "S", "XL", "2XL"],
    "sellingPrice": 1124,
    "marketPrice": 2499,
    "percentageDiscount": 55,
    "faltDiscount": "",
    "inventory": 10,
    "collections": "Men",
    "subCollection": "Topwear",
    "gender": "Men",
    "category": "T-Shirts"
  },
  {
    "image": "https://assets.myntassets.com/dpr_2,q_60,w_210,c_limit,fl_progressive/assets/images/20492030/2022/10/21/9722200e-86eb-4518-be39-fa53e827ed501666357402137Tshirts1.jpg",
    "brand": "Classic Polo",
    "color": "Multy",
    "title": "Men Striped Cotton T-shirt",
    "size": ["M", "XL", "2XL", "3XL"],
    "sellingPrice": 0,
    "marketPrice": 0,
    "percentageDiscount": "",
    "faltDiscount": "",
    "inventory": 10,
    "collections": "Men",
    "subCollection": "Topwear",
    "gender": "Men",
    "category": "T-Shirts"
  },
  {
    "image": "https://assets.myntassets.com/dpr_2,q_60,w_210,c_limit,fl_progressive/assets/images/18490134/2022/5/28/0650805f-9630-413a-8967-ffea6ffd32231653727454237MensPackof2RoundNeckTshirt1.jpg",
    "brand": "ARDEUR",
    "color": "Multy",
    "title": "Men Pack Of 2 T-shirt",
    "size": ["XS", "XL", "2XL", "3XL"],
    "sellingPrice": 499,
    "marketPrice": 1998,
    "percentageDiscount": 75,
    "faltDiscount": "",
    "inventory": 10,
    "collections": "Men",
    "subCollection": "Topwear",
    "gender": "Men",
    "category": "T-Shirts"
  },
  {
    "image": "https://assets.myntassets.com/dpr_2,q_60,w_210,c_limit,fl_progressive/assets/images/16860316/2022/6/4/326889f0-b11a-49fe-b529-53e2ab04b3bb1654336795445-BEAT-LONDON-by-PEPE-JEANS-Men-Multicoloured-Printed-Cowl-Nec-1.jpg",
    "brand": "BEAT LONDON by PEPE JEANS",
    "color": "Multy",
    "title": "Men Printed Cowl Neck Slim Fit T-shirt",
    "size": ["XS", "XL", "2XL", "3XL"],
    "sellingPrice": 623,
    "marketPrice": 1199,
    "percentageDiscount": 48,
    "faltDiscount": "",
    "inventory": 10,
    "collections": "Men",
    "subCollection": "Topwear",
    "gender": "Men",
    "category": "T-Shirts"
  },
  {
    "image": "https://assets.myntassets.com/dpr_2,q_60,w_210,c_limit,fl_progressive/assets/images/19938462/2022/9/12/9e067483-f626-44db-be5a-a06557f9c6561663002998926VanHeusenSportMenMulticolouredStripedT-shirt1.jpg",
    "brand": "Van Heusen Sport",
    "color": "Multy",
    "title": "Men Striped T-shirt",
    "size": ["S", "L", "XL", "3XL"],
    "sellingPrice": 974,
    "marketPrice": 1299,
    "percentageDiscount": 25,
    "faltDiscount": "",
    "inventory": 10,
    "collections": "Men",
    "subCollection": "Topwear",
    "gender": "Men",
    "category": "T-Shirts"
  },
  {
    "image": "https://assets.myntassets.com/dpr_2,q_60,w_210,c_limit,fl_progressive/assets/images/20461290/2022/10/19/c23252d8-d396-4c3e-b809-f87d40cf77101666175712194LouisPhilippeMulticolouredT-shirt1.jpg",
    "brand": "Louis Philippe Sport",
    "color": "Multy",
    "title": "Men Colourblocked Slim Fit T-shirt",
    "size": ["L", "XL", "2XL", "3XL"],
    "sellingPrice": 0,
    "marketPrice": 0,
    "percentageDiscount": "",
    "faltDiscount": "",
    "inventory": 10,
    "collections": "Men",
    "subCollection": "Topwear",
    "gender": "Men",
    "category": "T-Shirts"
  },
  {
    "image": "https://assets.myntassets.com/dpr_2,q_60,w_210,c_limit,fl_progressive/assets/images/18163118/2022/10/4/20ccd5ae-d9d0-48cf-95cc-92ad04bcfd5e1664880060421-Fleximaa-Men-Multicoloured-Set-of-2-Polo-Collar-T-shirt-6216-1.jpg",
    "brand": "Fleximaa",
    "color": "Multy",
    "title": "Men Polo Collar T-shirt",
    "size": ["XS", "L", "2XL", "3XL"],
    "sellingPrice": 819,
    "marketPrice": 2999,
    "percentageDiscount": "",
    "faltDiscount": 2180,
    "inventory": 10,
    "collections": "Men",
    "subCollection": "Topwear",
    "gender": "Men",
    "category": "T-Shirts"
  },
  {
    "image": "https://assets.myntassets.com/dpr_2,q_60,w_210,c_limit,fl_progressive/assets/images/18293980/2022/5/17/1b7ad80b-fe56-499f-8471-1a14414dc9cf1652727711698bigbananaMenMulticolouredColourblockedPoloCollarAppliqueT-sh1.jpg",
    "brand": "bigbanana",
    "color": "Multy",
    "title": "Men Colourblocked Polo Collar Applique T-shirt",
    "size": ["XS", "S", "M", "XL"],
    "sellingPrice": 799,
    "marketPrice": 1999,
    "percentageDiscount": 60,
    "faltDiscount": "",
    "inventory": 10,
    "collections": "Men",
    "subCollection": "Topwear",
    "gender": "Men",
    "category": "T-Shirts"
  },
  {
    "image": "https://assets.myntassets.com/dpr_2,q_60,w_210,c_limit,fl_progressive/assets/images/productimage/2021/1/20/67ef718d-49d6-45a8-ac27-9042f377abb11611155084970-1.jpg",
    "brand": "Dollar",
    "color": "Multy",
    "title": "Solid Polo Collar T-shirt",
    "size": ["XS", "S", "M", "L"],
    "sellingPrice": 843,
    "marketPrice": 1298,
    "percentageDiscount": 35,
    "faltDiscount": "",
    "inventory": 10,
    "collections": "Men",
    "subCollection": "Topwear",
    "gender": "Men",
    "category": "T-Shirts"
  },
  {
    "image": "https://assets.myntassets.com/dpr_2,q_60,w_210,c_limit,fl_progressive/assets/images/productimage/2021/6/27/82f26d39-f530-4fbc-a76a-40b8dc432d321624795320885-1.jpg",
    "brand": "PAUSE SPORT",
    "color": "Multy",
    "title": "Men Colourblocked Slim Fit T-shirt",
    "size": ["XS", "M", "L", "3XL"],
    "sellingPrice": 309,
    "marketPrice": 999,
    "percentageDiscount": 69,
    "faltDiscount": "",
    "inventory": 10,
    "collections": "Men",
    "subCollection": "Topwear",
    "gender": "Men",
    "category": "T-Shirts"
  },
  {
    "image": "https://assets.myntassets.com/dpr_2,q_60,w_210,c_limit,fl_progressive/assets/images/1897576/2017/5/10/11494417491965-Wear-Your-Mind-Men-Tshirts-8811494417491748-1.jpg",
    "brand": "Wear Your Mind",
    "color": "Multy",
    "title": "Printed Round Neck T-shirt",
    "size": ["S", "M", "XL", "2XL"],
    "sellingPrice": 384,
    "marketPrice": 1099,
    "percentageDiscount": 65,
    "faltDiscount": "",
    "inventory": 10,
    "collections": "Men",
    "subCollection": "Topwear",
    "gender": "Men",
    "category": "T-Shirts"
  },
  {
    "image": "https://assets.myntassets.com/dpr_2,q_60,w_210,c_limit,fl_progressive/assets/images/productimage/2019/6/3/0bd27cc4-c51f-4793-9663-097690798c811559546169859-1.jpg",
    "brand": "bigbanana",
    "color": "Multy",
    "title": "Plus Size Colourblocked Henley Neck Pure Cotton T-shirt",
    "size": ["XS", "S", "M", "3XL"],
    "sellingPrice": 719,
    "marketPrice": 1599,
    "percentageDiscount": 55,
    "faltDiscount": "",
    "inventory": 10,
    "collections": "Men",
    "subCollection": "Topwear",
    "gender": "Men",
    "category": "T-Shirts"
  },
  {
    "image": "https://assets.myntassets.com/dpr_2,q_60,w_210,c_limit,fl_progressive/assets/images/16540390/2021/12/17/2a216087-8360-4e69-b572-cd4890568fb31639723366515Tshirts1.jpg",
    "brand": "Classic Polo",
    "color": "Multy",
    "title": "Men Polo Collar Slim Fit T-shirt",
    "size": ["XS", "S", "M", "XL"],
    "sellingPrice": 0,
    "marketPrice": 0,
    "percentageDiscount": "",
    "faltDiscount": "",
    "inventory": 10,
    "collections": "Men",
    "subCollection": "Topwear",
    "gender": "Men",
    "category": "T-Shirts"
  },
  {
    "image": "https://assets.myntassets.com/dpr_2,q_60,w_210,c_limit,fl_progressive/assets/images/21167228/2022/12/12/5bf6872c-cada-4776-aba5-23a610d639c31670858188438bigbananaBrovin-MultiMenPlusSizeMultiStripedRoundNeckTshirt1.jpg",
    "brand": "bigbanana",
    "color": "Multy",
    "title": "Plus Size Bio Finish T-shirt",
    "size": ["M", "L", "XL", "3XL"],
    "sellingPrice": 679,
    "marketPrice": 1699,
    "percentageDiscount": 60,
    "faltDiscount": "",
    "inventory": 10,
    "collections": "Men",
    "subCollection": "Topwear",
    "gender": "Men",
    "category": "T-Shirts"
  },
  {
    "image": "https://assets.myntassets.com/dpr_2,q_60,w_210,c_limit,fl_progressive/assets/images/16291084/2021/11/29/710a8237-649a-413e-ab13-e4f584ab4c1d1638184112888DollarMensTshirt1.jpg",
    "brand": "Dollar",
    "color": "Multy",
    "title": "5 Pcs Polo Collar T-shirts",
    "size": ["XS", "S", "M", "2XL"],
    "sellingPrice": 1947,
    "marketPrice": 3245,
    "percentageDiscount": 40,
    "faltDiscount": "",
    "inventory": 10,
    "collections": "Men",
    "subCollection": "Topwear",
    "gender": "Men",
    "category": "T-Shirts"
  },
  {
    "image": "https://assets.myntassets.com/dpr_2,q_60,w_210,c_limit,fl_progressive/assets/images/16790882/2022/3/5/3dccb209-6b95-4ddc-8961-a685c0b75f5f1646479609373ORIGINBYZALORAMenMulticolouredStripeCrewNeckLinenT-Shirt1.jpg",
    "brand": "ORIGIN BY ZALORA",
    "color": "Multy",
    "title": "Men Striped T-shirt",
    "size": ["XS", "M", "2XL", "3XL"],
    "sellingPrice": 1979,
    "marketPrice": 3599,
    "percentageDiscount": 45,
    "faltDiscount": "",
    "inventory": 10,
    "collections": "Men",
    "subCollection": "Topwear",
    "gender": "Men",
    "category": "T-Shirts"
  },
  {
    "image": "https://assets.myntassets.com/dpr_2,q_60,w_210,c_limit,fl_progressive/assets/images/productimage/2021/3/10/a17f8980-4982-440c-873d-56172571a4331615378879052-1.jpg",
    "brand": "Kalt",
    "color": "Multy",
    "title": "Colourblocked Polo Collar T-shirt",
    "size": ["XS", "S", "XL", "3XL"],
    "sellingPrice": 660,
    "marketPrice": 1200,
    "percentageDiscount": 45,
    "faltDiscount": "",
    "inventory": 10,
    "collections": "Men",
    "subCollection": "Topwear",
    "gender": "Men",
    "category": "T-Shirts"
  },
  {
    "image": "https://assets.myntassets.com/dpr_2,q_60,w_210,c_limit,fl_progressive/assets/images/productimage/2021/3/1/38532280-6d23-4a17-a3e9-49851161668a1614611007648-1.jpg",
    "brand": "Rodamo",
    "color": "Multy",
    "title": "Striped Polo Collar T-shirt",
    "size": ["XS", "L", "XL", "3XL"],
    "sellingPrice": 529,
    "marketPrice": 999,
    "percentageDiscount": 47,
    "faltDiscount": "",
    "inventory": 10,
    "collections": "Men",
    "subCollection": "Topwear",
    "gender": "Men",
    "category": "T-Shirts"
  },
  {
    "image": "https://assets.myntassets.com/dpr_2,q_60,w_210,c_limit,fl_progressive/assets/images/17817104/2022/4/13/92e6f482-c527-438d-9fba-358cd783f66e1649848067297TshirtsTrendyolMenTshirtsTrendyolMenTshirtsTrendyolMenTshirt1.jpg",
    "brand": "Trendyol",
    "color": "Multy",
    "title": "Printed Cotton Hooded T-shirt",
    "size": ["S", "M", "XL", "3XL"],
    "sellingPrice": 549,
    "marketPrice": 1099,
    "percentageDiscount": 50,
    "faltDiscount": "",
    "inventory": 10,
    "collections": "Men",
    "subCollection": "Topwear",
    "gender": "Men",
    "category": "T-Shirts"
  },
  {
    "image": "https://assets.myntassets.com/dpr_2,q_60,w_210,c_limit,fl_progressive/assets/images/18928400/2022/7/11/c2396d65-7c15-4e89-b3ef-2ca96a14567d1657518784672FlyingMachineMenMulticolouredPrintedT-shirt1.jpg",
    "brand": "Flying Machine",
    "color": "Multy",
    "title": "Men Printed T-shirt",
    "size": ["XS", "L", "XL", "2XL"],
    "sellingPrice": 599,
    "marketPrice": 999,
    "percentageDiscount": 40,
    "faltDiscount": "",
    "inventory": 10,
    "collections": "Men",
    "subCollection": "Topwear",
    "gender": "Men",
    "category": "T-Shirts"
  },
  {
    "image": "https://assets.myntassets.com/dpr_2,q_60,w_210,c_limit,fl_progressive/assets/images/productimage/2019/6/3/463e716a-8838-4bbc-9932-c3c5a1df5f8c1559554133898-1.jpg",
    "brand": "bigbanana",
    "color": "Multy",
    "title": "Plus Size Colourblocked Mandarin Collar Pure Cotton T-shirt",
    "size": ["XS", "S", "XL", "2XL"],
    "sellingPrice": 594,
    "marketPrice": 1699,
    "percentageDiscount": 65,
    "faltDiscount": "",
    "inventory": 10,
    "collections": "Men",
    "subCollection": "Topwear",
    "gender": "Men",
    "category": "T-Shirts"
  },
  {
    "image": "https://assets.myntassets.com/dpr_2,q_60,w_210,c_limit,fl_progressive/assets/images/18838656/2022/6/23/fc816f1b-e893-40fd-ac57-e965866435e31655972028625UrGearMenMulticolorColorblockedRoundNeckHalfSleeveCasualT-Sh1.jpg",
    "brand": "UrGear",
    "color": "Multy",
    "title": "Men Colourblocked T-shirt",
    "size": ["XS", "S", "M", "L"],
    "sellingPrice": 571,
    "marketPrice": 2199,
    "percentageDiscount": 74,
    "faltDiscount": "",
    "inventory": 10,
    "collections": "Men",
    "subCollection": "Topwear",
    "gender": "Men",
    "category": "T-Shirts"
  },
  {
    "image": "https://assets.myntassets.com/dpr_2,q_60,w_210,c_limit,fl_progressive/assets/images/18732826/2022/6/15/ac9eab25-944b-4faa-af33-380daf8fad501655281145566LouisPhilippeMulticolouredT-shirt1.jpg",
    "brand": "Louis Philippe Jeans",
    "color": "Multy",
    "title": "Men Striped Polo Collar Applique Slim Fit T-shirt",
    "size": ["XS", "M", "2XL", "3XL"],
    "sellingPrice": 1699,
    "marketPrice": 1999,
    "percentageDiscount": 15,
    "faltDiscount": "",
    "inventory": 10,
    "collections": "Men",
    "subCollection": "Topwear",
    "gender": "Men",
    "category": "T-Shirts"
  },
  {
    "image": "https://assets.myntassets.com/dpr_2,q_60,w_210,c_limit,fl_progressive/assets/images/productimage/2021/3/23/c4e8f785-66ee-4507-b9e4-0fa41c002b661616475537566-1.jpg",
    "brand": "Dollar",
    "color": "Multy",
    "title": "Pack of 2 Solid T-shirt",
    "size": ["XS", "M", "L", "XL"],
    "sellingPrice": 544,
    "marketPrice": 838,
    "percentageDiscount": 35,
    "faltDiscount": "",
    "inventory": 10,
    "collections": "Men",
    "subCollection": "Topwear",
    "gender": "Men",
    "category": "T-Shirts"
  },
  {
    "image": "https://assets.myntassets.com/dpr_2,q_60,w_210,c_limit,fl_progressive/assets/images/18224432/2022/5/11/1127e10e-68aa-4aaa-98f1-36b263cfd5c81652237991392UnitedColorsofBenettonMenMulticolouredStripedPoloCollarAppli1.jpg",
    "brand": "United Colors of Benetton",
    "color": "Multy",
    "title": "Men Striped  T-shirt",
    "size": ["M", "L", "XL", "3XL"],
    "sellingPrice": 1609,
    "marketPrice": 2299,
    "percentageDiscount": 30,
    "faltDiscount": "",
    "inventory": 10,
    "collections": "Men",
    "subCollection": "Topwear",
    "gender": "Men",
    "category": "T-Shirts"
  },
  {
    "image": "https://assets.myntassets.com/dpr_2,q_60,w_210,c_limit,fl_progressive/assets/images/18471228/2022/5/27/16cdddec-1d72-401f-a785-112463aa58981653656786307Tshirts1.jpg",
    "brand": "United Colors of Benetton",
    "color": "Multy",
    "title": "Men Striped Polo Collar T-shirt",
    "size": ["S", "L", "XL", "2XL"],
    "sellingPrice": 1379,
    "marketPrice": 2299,
    "percentageDiscount": 40,
    "faltDiscount": "",
    "inventory": 10,
    "collections": "Men",
    "subCollection": "Topwear",
    "gender": "Men",
    "category": "T-Shirts"
  },
  {
    "image": "https://assets.myntassets.com/dpr_2,q_60,w_210,c_limit,fl_progressive/assets/images/18942468/2022/7/1/bc53f22f-5cb5-4c15-b07d-35f80301cae11656684380726MenMultiTankTop1.jpg",
    "brand": "Peter England",
    "color": "Multy",
    "title": "Men Printed T-shirt",
    "size": ["XS", "M", "XL", "3XL"],
    "sellingPrice": 499,
    "marketPrice": 999,
    "percentageDiscount": 50,
    "faltDiscount": "",
    "inventory": 10,
    "collections": "Men",
    "subCollection": "Topwear",
    "gender": "Men",
    "category": "T-Shirts"
  },
  {
    "image": "https://assets.myntassets.com/dpr_2,q_60,w_210,c_limit,fl_progressive/assets/images/19446518/2022/8/9/18f87182-a522-4482-b406-7a16852f01a61660038927304LouisPhilippeMulticolouredT-shirt1.jpg",
    "brand": "Louis Philippe Sport",
    "color": "Multy",
    "title": "Men Colourblocked Polo Collar Applique Slim Fit T-shirt",
    "size": ["XS", "M", "XL", "2XL"],
    "sellingPrice": 2249,
    "marketPrice": 2499,
    "percentageDiscount": 10,
    "faltDiscount": "",
    "inventory": 10,
    "collections": "Men",
    "subCollection": "Topwear",
    "gender": "Men",
    "category": "T-Shirts"
  },
  {
    "image": "https://assets.myntassets.com/dpr_2,q_60,w_210,c_limit,fl_progressive/assets/images/4332347/2018/3/23/11521794095292-Wear-Your-Mind-Multicolor-Vest-For-Men-4641521794095083-1.jpg",
    "brand": "Wear Your Mind",
    "color": "Multy",
    "title": "Printed Scoop Neck T-shirt",
    "size": ["XS", "M", "XL", "3XL"],
    "sellingPrice": 399,
    "marketPrice": 999,
    "percentageDiscount": 60,
    "faltDiscount": "",
    "inventory": 10,
    "collections": "Men",
    "subCollection": "Topwear",
    "gender": "Men",
    "category": "T-Shirts"
  },
  {
    "image": "https://assets.myntassets.com/dpr_2,q_60,w_210,c_limit,fl_progressive/assets/images/4332216/2018/3/23/11521794038793-Wear-Your-Mind-Multicolor-Vest-For-Men-51521794038488-1.jpg",
    "brand": "Wear Your Mind",
    "color": "Multy",
    "title": "Printed Scoop Neck T-shirt",
    "size": ["XS", "L", "XL", "2XL"],
    "sellingPrice": 399,
    "marketPrice": 999,
    "percentageDiscount": 60,
    "faltDiscount": "",
    "inventory": 10,
    "collections": "Men",
    "subCollection": "Topwear",
    "gender": "Men",
    "category": "T-Shirts"
  },
  {
    "image": "https://assets.myntassets.com/dpr_2,q_60,w_210,c_limit,fl_progressive/assets/images/2417028/2018/1/22/11516605032625-Wear-Your-Mind-Men-Multicoloured-Printed-Round-Neck-T-shirt-761516605032487-1.jpg",
    "brand": "Wear Your Mind",
    "color": "Multy",
    "title": "Printed Round Neck T-shirt",
    "size": ["S", "M", "2XL", "3XL"],
    "sellingPrice": 391,
    "marketPrice": 1349,
    "percentageDiscount": 71,
    "faltDiscount": "",
    "inventory": 10,
    "collections": "Men",
    "subCollection": "Topwear",
    "gender": "Men",
    "category": "T-Shirts"
  },
  {
    "image": "https://assets.myntassets.com/dpr_2,q_60,w_210,c_limit,fl_progressive/assets/images/16060204/2022/2/14/06568e4c-42a3-4d45-b6d7-a167c9bb8ec11644818124499-abof-Men-Multicoloured--Red-Printed-Polo-Collar-Casual-T-shi-1.jpg",
    "brand": "abof",
    "color": "Multy",
    "title": "Men Printed Polo Collar T-shirt",
    "size": ["XS", "M", "XL", "2XL"],
    "sellingPrice": 359,
    "marketPrice": 1199,
    "percentageDiscount": 70,
    "faltDiscount": "",
    "inventory": 10,
    "collections": "Men",
    "subCollection": "Topwear",
    "gender": "Men",
    "category": "T-Shirts"
  },
  {
    "image": "https://assets.myntassets.com/dpr_2,q_60,w_210,c_limit,fl_progressive/assets/images/20492056/2022/10/21/b281bd55-dc2e-47e7-88f0-a653e19bf7771666355825347Tshirts1.jpg",
    "brand": "Classic Polo",
    "color": "Multy",
    "title": "Men Striped Cotton T-shirt",
    "size": ["M", "L", "XL", "3XL"],
    "sellingPrice": 0,
    "marketPrice": 0,
    "percentageDiscount": "",
    "faltDiscount": "",
    "inventory": 10,
    "collections": "Men",
    "subCollection": "Topwear",
    "gender": "Men",
    "category": "T-Shirts"
  },
  {
    "image": "https://assets.myntassets.com/dpr_2,q_60,w_210,c_limit,fl_progressive/assets/images/17540558/2022/3/15/9321e1f8-a2b1-4d1e-bba4-b3beb4d4474f1647351490619SELECTEDMenMulticolouredStripedExtendedSleevesOrganicCottonT1.jpg",
    "brand": "SELECTED",
    "color": "Multy",
    "title": "Men Striped T-shirt",
    "size": ["XS", "M", "L", "3XL"],
    "sellingPrice": 1199,
    "marketPrice": 1999,
    "percentageDiscount": 40,
    "faltDiscount": "",
    "inventory": 10,
    "collections": "Men",
    "subCollection": "Topwear",
    "gender": "Men",
    "category": "T-Shirts"
  },
  {
    "image": "https://assets.myntassets.com/dpr_2,q_60,w_210,c_limit,fl_progressive/assets/images/20491842/2022/10/21/98157d38-bbf2-4166-adfd-3c15b0a5b4511666354855495Tshirts1.jpg",
    "brand": "Duke",
    "color": "Multy",
    "title": "Men Polo Collar Cotton T-shirt",
    "size": ["L", "XL", "2XL", "3XL"],
    "sellingPrice": 906,
    "marketPrice": 1295,
    "percentageDiscount": 30,
    "faltDiscount": "",
    "inventory": 10,
    "collections": "Men",
    "subCollection": "Topwear",
    "gender": "Men",
    "category": "T-Shirts"
  },
  {
    "image": "https://assets.myntassets.com/dpr_2,q_60,w_210,c_limit,fl_progressive/assets/images/17635112/2022/3/24/8f38fd9a-61b6-4fa6-b140-6da05c48dd841648139219892CrimsouneClubMenMulticolouredStripedPoloCollarSlimFitOutdoor1.jpg",
    "brand": "Crimsoune Club",
    "color": "Multy",
    "title": "Men Striped Polo Collar Slim Fit T-shirt",
    "size": ["S", "XL", "2XL", "3XL"],
    "sellingPrice": 899,
    "marketPrice": 1499,
    "percentageDiscount": 40,
    "faltDiscount": "",
    "inventory": 10,
    "collections": "Men",
    "subCollection": "Topwear",
    "gender": "Men",
    "category": "T-Shirts"
  },
  {
    "image": "https://assets.myntassets.com/dpr_2,q_60,w_210,c_limit,fl_progressive/assets/images/18175210/2022/5/6/f56d1102-1b15-4cd7-a056-ac5b70aed73c1651834859294JovenMenMulticolouredBioFinishSlimFitT-shirt1.jpg",
    "brand": "Joven",
    "color": "Multy",
    "title": "Men Pack Of 3 Slim Fit T-shirt",
    "size": ["XS", "L", "2XL", "3XL"],
    "sellingPrice": 899,
    "marketPrice": 2999,
    "percentageDiscount": 70,
    "faltDiscount": "",
    "inventory": 10,
    "collections": "Men",
    "subCollection": "Topwear",
    "gender": "Men",
    "category": "T-Shirts"
  },
  {
    "image": "https://assets.myntassets.com/dpr_2,q_60,w_210,c_limit,fl_progressive/assets/images/17988022/2022/4/22/90417266-1263-4652-aee8-ae98c2637c761650620147801DukeMenMulticolouredTypography3PrintedAppliqueSlimFitT-shirt1.jpg",
    "brand": "Duke",
    "color": "Multy",
    "title": "Men Pack Of 3 T-shirts",
    "size": ["XS", "M", "L", "3XL"],
    "sellingPrice": 959,
    "marketPrice": 1199,
    "percentageDiscount": 20,
    "faltDiscount": "",
    "inventory": 10,
    "collections": "Men",
    "subCollection": "Topwear",
    "gender": "Men",
    "category": "T-Shirts"
  },
  {
    "image": "https://assets.myntassets.com/dpr_2,q_60,w_210,c_limit,fl_progressive/assets/images/productimage/2021/1/21/22678ade-6ae7-4b54-9d36-dfd5e72c9dcc1611227992573-1.jpg",
    "brand": "Dollar",
    "color": "Multy",
    "title": "Solid Polo Collar T-shirt",
    "size": ["M", "L", "XL", "3XL"],
    "sellingPrice": 843,
    "marketPrice": 1298,
    "percentageDiscount": 35,
    "faltDiscount": "",
    "inventory": 10,
    "collections": "Men",
    "subCollection": "Topwear",
    "gender": "Men",
    "category": "T-Shirts"
  },
  {
    "image": "https://assets.myntassets.com/dpr_2,q_60,w_210,c_limit,fl_progressive/assets/images/18529640/2022/5/31/f6b18494-4082-443e-99fd-27268f76d6031653986641024MenMultiPoloTShirt1.jpg",
    "brand": "Peter England Casuals",
    "color": "Multy",
    "title": "Men Striped Polo Collar Slim Fit T-shirt",
    "size": ["M", "L", "2XL", "3XL"],
    "sellingPrice": 839,
    "marketPrice": 1399,
    "percentageDiscount": 40,
    "faltDiscount": "",
    "inventory": 10,
    "collections": "Men",
    "subCollection": "Topwear",
    "gender": "Men",
    "category": "T-Shirts"
  },
  {
    "image": "https://assets.myntassets.com/dpr_2,q_60,w_210,c_limit,fl_progressive/assets/images/18849788/2022/6/23/b7ecad24-b61d-4f3e-846a-86f6d5773c111656007853901FleximaaMensCottonRoundNeckHalfSleeveT-ShirtPackof31.jpg",
    "brand": "Fleximaa",
    "color": "Multy",
    "title": "Men T-shirt",
    "size": ["M", "L", "XL", "3XL"],
    "sellingPrice": 839,
    "marketPrice": 840,
    "percentageDiscount": "",
    "faltDiscount": 1,
    "inventory": 10,
    "collections": "Men",
    "subCollection": "Topwear",
    "gender": "Men",
    "category": "T-Shirts"
  },
  {
    "image": "https://assets.myntassets.com/dpr_2,q_60,w_210,c_limit,fl_progressive/assets/images/19653102/2022/8/25/1cd035a5-9c39-44e5-94ae-99f49efbc5e91661414302112Tshirts1.jpg",
    "brand": "Duke",
    "color": "Multy",
    "title": "Men Slim Fit T-shirt",
    "size": ["XS", "S", "2XL", "3XL"],
    "sellingPrice": 836,
    "marketPrice": 1195,
    "percentageDiscount": 30,
    "faltDiscount": "",
    "inventory": 10,
    "collections": "Men",
    "subCollection": "Topwear",
    "gender": "Men",
    "category": "T-Shirts"
  },
  {
    "image": "https://assets.myntassets.com/dpr_2,q_60,w_210,c_limit,fl_progressive/assets/images/18293970/2022/5/17/223d8d89-e93a-4988-a356-78fa0e26c9a31652727729699bigbananaMenMulticolouredStripedPoloCollarT-shirt1.jpg",
    "brand": "bigbanana",
    "color": "Multy",
    "title": "Men Striped Polo Collar T-shirt",
    "size": ["XS", "S", "XL", "3XL"],
    "sellingPrice": 799,
    "marketPrice": 1999,
    "percentageDiscount": 60,
    "faltDiscount": "",
    "inventory": 10,
    "collections": "Men",
    "subCollection": "Topwear",
    "gender": "Men",
    "category": "T-Shirts"
  },
  {
    "image": "https://assets.myntassets.com/dpr_2,q_60,w_210,c_limit,fl_progressive/assets/images/18387080/2022/5/23/d5832e20-37b1-45e0-a7e8-bf460e8379fd1653314775031ADByArvindMenMulticolouredPrintedPoloCollarSlimFitT-shirt1.jpg",
    "brand": "AD By Arvind",
    "color": "Multy",
    "title": "Men 100% Cotton T-shirt",
    "size": ["L", "XL", "2XL", "3XL"],
    "sellingPrice": 799,
    "marketPrice": 1599,
    "percentageDiscount": 50,
    "faltDiscount": "",
    "inventory": 10,
    "collections": "Men",
    "subCollection": "Topwear",
    "gender": "Men",
    "category": "T-Shirts"
  },
  {
    "image": "https://assets.myntassets.com/dpr_2,q_60,w_210,c_limit,fl_progressive/assets/images/19322050/2022/7/30/93cc144e-7935-483e-907b-0ca78787e7461659194561480DollarMenMulticoloured2PoloCollarT-shirt1.jpg",
    "brand": "Dollar",
    "color": "Multy",
    "title": "Men Polo Collar T-shirt",
    "size": ["L", "XL", "2XL", "3XL"],
    "sellingPrice": 843,
    "marketPrice": 1298,
    "percentageDiscount": 35,
    "faltDiscount": "",
    "inventory": 10,
    "collections": "Men",
    "subCollection": "Topwear",
    "gender": "Men",
    "category": "T-Shirts"
  },
  {
    "image": "https://assets.myntassets.com/dpr_2,q_60,w_210,c_limit,fl_progressive/assets/images/19571014/2022/8/20/2d2e65a4-de6c-4857-8ea1-f9f5a2ec67091660983519552CPBROMenMulticolouredCamouflagePrintedRawEdgeSlimFitT-shirt1.jpg",
    "brand": "CP BRO",
    "color": "Multy",
    "title": "Men Camouflage Printed Slim Fit T-shirt",
    "size": ["XS", "L", "XL", "3XL"],
    "sellingPrice": 0,
    "marketPrice": 0,
    "percentageDiscount": "",
    "faltDiscount": "",
    "inventory": 10,
    "collections": "Men",
    "subCollection": "Topwear",
    "gender": "Men",
    "category": "T-Shirts"
  },
  {
    "image": "https://assets.myntassets.com/dpr_2,q_60,w_210,c_limit,fl_progressive/assets/images/18214476/2022/7/5/62c11ad4-f265-4681-9c71-7c013f6732f91657041250298HubberholmeMenRoundNeckMulticolouredPackof2T-shirt1.jpg",
    "brand": "Hubberholme",
    "color": "Multy",
    "title": "Men Pack of 2 T-shirt",
    "size": ["XS", "L", "2XL", "3XL"],
    "sellingPrice": 664,
    "marketPrice": 1899,
    "percentageDiscount": 65,
    "faltDiscount": "",
    "inventory": 10,
    "collections": "Men",
    "subCollection": "Topwear",
    "gender": "Men",
    "category": "T-Shirts"
  },
  {
    "image": "https://assets.myntassets.com/dpr_2,q_60,w_210,c_limit,fl_progressive/assets/images/11786322/2020/4/7/13169ab7-8883-4dca-b4c4-130c1026eced1586253958364VIMALJONNEYMenMulticolouredStripedRoundNeckT-shirt1.jpg",
    "brand": "VIMAL JONNEY",
    "color": "Multy",
    "title": "Pack Of 2 Round Neck T-shirt",
    "size": ["S", "M", "L", "2XL"],
    "sellingPrice": 739,
    "marketPrice": 1998,
    "percentageDiscount": 63,
    "faltDiscount": "",
    "inventory": 10,
    "collections": "Men",
    "subCollection": "Topwear",
    "gender": "Men",
    "category": "T-Shirts"
  },
  {
    "image": "https://assets.myntassets.com/dpr_2,q_60,w_210,c_limit,fl_progressive/assets/images/18849860/2022/6/23/34b99afd-ecea-4fc7-95c3-799a878f64e51656003486244FleximaaMensPrintedSleevelessPackof21.jpg",
    "brand": "Fleximaa",
    "color": "Multy",
    "title": "Men Typography Printed Raw Edge T-shirt",
    "size": ["S", "M", "2XL", "3XL"],
    "sellingPrice": 549,
    "marketPrice": 899,
    "percentageDiscount": "",
    "faltDiscount": 350,
    "inventory": 10,
    "collections": "Men",
    "subCollection": "Topwear",
    "gender": "Men",
    "category": "T-Shirts"
  },
  {
    "image": "https://assets.myntassets.com/dpr_2,q_60,w_210,c_limit,fl_progressive/assets/images/14845144/2021/8/18/e5cf9003-d2ed-4d1b-879f-b1c4adf112241629283593180-mezmoda-Men-Tshirts-541629283592594-1.jpg",
    "brand": "mezmoda",
    "color": "Multy",
    "title": "Men Printed T-shirt",
    "size": ["XS", "S", "L", "2XL"],
    "sellingPrice": 544,
    "marketPrice": 1815,
    "percentageDiscount": 70,
    "faltDiscount": "",
    "inventory": 10,
    "collections": "Men",
    "subCollection": "Topwear",
    "gender": "Men",
    "category": "T-Shirts"
  },
  {
    "image": "https://assets.myntassets.com/dpr_2,q_60,w_210,c_limit,fl_progressive/assets/images/20010112/2022/9/15/45276436-1bb9-49a3-8e12-815c95bd2e6f1663266005388AllenSollyMenMulticolouredColourblockedPoloCollarT-shirt1.jpg",
    "brand": "Allen Solly",
    "color": "Multy",
    "title": "Men Colourblocked Polo Collar T-shirt",
    "size": ["XS", "M", "XL", "3XL"],
    "sellingPrice": 1779,
    "marketPrice": 1999,
    "percentageDiscount": 11,
    "faltDiscount": "",
    "inventory": 10,
    "collections": "Men",
    "subCollection": "Topwear",
    "gender": "Men",
    "category": "T-Shirts"
  },
  {
    "image": "https://assets.myntassets.com/dpr_2,q_60,w_210,c_limit,fl_progressive/assets/images/20092210/2022/9/20/c1cb5ebc-abde-48ab-ad07-c6377de72edc1663673962138AllenSollyMulticolouredTShirt1.jpg",
    "brand": "Allen Solly",
    "color": "Multy",
    "title": "Colourblocked Cotton T-shirt",
    "size": ["XS", "S", "L", "XL"],
    "sellingPrice": 2046,
    "marketPrice": 2299,
    "percentageDiscount": 11,
    "faltDiscount": "",
    "inventory": 10,
    "collections": "Men",
    "subCollection": "Topwear",
    "gender": "Men",
    "category": "T-Shirts"
  },
  {
    "image": "https://assets.myntassets.com/dpr_2,q_60,w_210,c_limit,fl_progressive/assets/images/20092236/2022/9/20/7961f051-11fe-4734-aae4-ce7c9abb0fb21663673194026AllenSollyMulticolouredTShirt1.jpg",
    "brand": "Allen Solly",
    "color": "Multy",
    "title": "Colourblocked Cotton T-shirt",
    "size": ["L", "XL", "2XL", "3XL"],
    "sellingPrice": 2046,
    "marketPrice": 2299,
    "percentageDiscount": 11,
    "faltDiscount": "",
    "inventory": 10,
    "collections": "Men",
    "subCollection": "Topwear",
    "gender": "Men",
    "category": "T-Shirts"
  },
  {
    "image": "https://assets.myntassets.com/dpr_2,q_60,w_210,c_limit,fl_progressive/assets/images/18849580/2022/6/23/1671a9f3-aa85-40d9-9de6-6bced4a869d01656002537071FleximaaMensCottonRoundNeckPrintedHalfSleevePackof21.jpg",
    "brand": "Fleximaa",
    "color": "Multy",
    "title": "Men Printed Raw Edge T-shirt",
    "size": ["S", "M", "L", "3XL"],
    "sellingPrice": 569,
    "marketPrice": 1199,
    "percentageDiscount": "",
    "faltDiscount": 630,
    "inventory": 10,
    "collections": "Men",
    "subCollection": "Topwear",
    "gender": "Men",
    "category": "T-Shirts"
  },
  {
    "image": "https://assets.myntassets.com/dpr_2,q_60,w_210,c_limit,fl_progressive/assets/images/17341696/2022/3/2/19dc685e-1577-4c2b-bd5c-b1eda11a55131646200888472KaltMenGreyColourblockedMandarinCollarT-shirt1.jpg",
    "brand": "Kalt",
    "color": "Multy",
    "title": "Men Colourblocked Mandarin Collar T-shirt",
    "size": ["S", "L", "2XL", "3XL"],
    "sellingPrice": 487,
    "marketPrice": 750,
    "percentageDiscount": 35,
    "faltDiscount": "",
    "inventory": 10,
    "collections": "Men",
    "subCollection": "Topwear",
    "gender": "Men",
    "category": "T-Shirts"
  },
  {
    "image": "https://assets.myntassets.com/dpr_2,q_60,w_210,c_limit,fl_progressive/assets/images/18529658/2022/5/31/57e79b98-0a6a-42b0-b252-c76b399643151653986643019MenMultiCrewNeckTShirt1.jpg",
    "brand": "Peter England Casuals",
    "color": "Multy",
    "title": "Men Colourblocked Slim Fit T-shirt",
    "size": ["S", "M", "XL", "2XL"],
    "sellingPrice": 449,
    "marketPrice": 899,
    "percentageDiscount": 50,
    "faltDiscount": "",
    "inventory": 10,
    "collections": "Men",
    "subCollection": "Topwear",
    "gender": "Men",
    "category": "T-Shirts"
  },
  {
    "image": "https://assets.myntassets.com/dpr_2,q_60,w_210,c_limit,fl_progressive/assets/images/14413556/2021/9/21/1b2ee714-2e77-435c-bdc5-6f97c25715c71632206345997-abof-Men-Tshirts-1601632206345399-1.jpg",
    "brand": "abof",
    "color": "Multy",
    "title": "Men Striped Polo Collar T-shirt",
    "size": ["XS", "M", "L", "3XL"],
    "sellingPrice": 419,
    "marketPrice": 1399,
    "percentageDiscount": 70,
    "faltDiscount": "",
    "inventory": 10,
    "collections": "Men",
    "subCollection": "Topwear",
    "gender": "Men",
    "category": "T-Shirts"
  },
  {
    "image": "https://assets.myntassets.com/dpr_2,q_60,w_210,c_limit,fl_progressive/assets/images/18145172/2022/5/4/5e238a70-c7ae-4b11-9078-adf56c1bb4ee1651673367977FleximaaMenMulticolouredTypographyPrintedT-shirt1.jpg",
    "brand": "Fleximaa",
    "color": "Multy",
    "title": "Men Typography Printed T-shirt",
    "size": ["XS", "S", "XL", "2XL"],
    "sellingPrice": 419,
    "marketPrice": 899,
    "percentageDiscount": "",
    "faltDiscount": 480,
    "inventory": 10,
    "collections": "Men",
    "subCollection": "Topwear",
    "gender": "Men",
    "category": "T-Shirts"
  },
  {
    "image": "https://assets.myntassets.com/dpr_2,q_60,w_210,c_limit,fl_progressive/assets/images/11031408/2019/11/23/4888c493-82a1-4d67-bdaf-87a57c7229461574485386133-Wear-Your-Mind-Polyester-Mens-T-shirt--Multi-285157448538421-1.jpg",
    "brand": "Wear Your Mind",
    "color": "Multy",
    "title": "Printed Round Neck T-shirt",
    "size": ["XS", "S", "M", "2XL"],
    "sellingPrice": 417,
    "marketPrice": 1099,
    "percentageDiscount": 62,
    "faltDiscount": "",
    "inventory": 10,
    "collections": "Men",
    "subCollection": "Topwear",
    "gender": "Men",
    "category": "T-Shirts"
  },
  {
    "image": "https://assets.myntassets.com/dpr_2,q_60,w_210,c_limit,fl_progressive/assets/images/2160711/2017/10/4/11507111166805-Marvel-Avengers-Men-Multicoloured-Printed-Round-Neck-T-shirt-6901507111166520-1.jpg",
    "brand": "Marvel by Wear Your Mind",
    "color": "Multy",
    "title": "Printed Round Neck T-shirt",
    "size": ["S", "M", "XL", "2XL"],
    "sellingPrice": 419,
    "marketPrice": 1399,
    "percentageDiscount": 70,
    "faltDiscount": "",
    "inventory": 10,
    "collections": "Men",
    "subCollection": "Topwear",
    "gender": "Men",
    "category": "T-Shirts"
  },
  {
    "image": "https://assets.myntassets.com/dpr_2,q_60,w_210,c_limit,fl_progressive/assets/images/productimage/2020/12/15/616c299a-7957-4642-ba41-5ef6146b26221608044525783-1.jpg",
    "brand": "Bishop Cotton",
    "color": "Multy",
    "title": "Colourblocked Round Neck T-shirt",
    "size": ["XS", "M", "2XL", "3XL"],
    "sellingPrice": 449,
    "marketPrice": 1799,
    "percentageDiscount": 75,
    "faltDiscount": "",
    "inventory": 10,
    "collections": "Men",
    "subCollection": "Topwear",
    "gender": "Men",
    "category": "T-Shirts"
  },
  {
    "image": "https://assets.myntassets.com/dpr_2,q_60,w_210,c_limit,fl_progressive/assets/images/20657158/2022/11/7/ba8636c4-43e9-476d-b610-1597f50f5dcc1667841376052PauseSportMultiSolidLongSleevesSlimFitRoundNeckMensT-Shirt1.jpg",
    "brand": "PAUSE SPORT",
    "color": "Multy",
    "title": "Men Colourblocked T-shirt",
    "size": ["XS", "M", "L", "XL"],
    "sellingPrice": 391,
    "marketPrice": 1399,
    "percentageDiscount": 72,
    "faltDiscount": "",
    "inventory": 10,
    "collections": "Men",
    "subCollection": "Topwear",
    "gender": "Men",
    "category": "T-Shirts"
  },
  {
    "image": "https://assets.myntassets.com/dpr_2,q_60,w_210,c_limit,fl_progressive/assets/images/7645943/2018/10/17/e27275e3-7869-4b73-bf6a-dd79e6d797cc1539765387867-NA-621539765387657-1.jpg",
    "brand": "Huetrap",
    "color": "Multy",
    "title": "Printed Round Neck T-shirt",
    "size": ["S", "XL", "2XL", "3XL"],
    "sellingPrice": 389,
    "marketPrice": 1499,
    "percentageDiscount": 74,
    "faltDiscount": "",
    "inventory": 10,
    "collections": "Men",
    "subCollection": "Topwear",
    "gender": "Men",
    "category": "T-Shirts"
  },
  {
    "image": "https://assets.myntassets.com/dpr_2,q_60,w_210,c_limit,fl_progressive/assets/images/2416979/2018/1/22/11516604977323-Wear-Your-Mind-Men-Multicoloured-Printed-Round-Neck-T-shirt-381516604977210-1.jpg",
    "brand": "Wear Your Mind",
    "color": "Multy",
    "title": "Printed Round Neck T-shirt",
    "size": ["S", "M", "XL", "3XL"],
    "sellingPrice": 349,
    "marketPrice": 999,
    "percentageDiscount": 65,
    "faltDiscount": "",
    "inventory": 10,
    "collections": "Men",
    "subCollection": "Topwear",
    "gender": "Men",
    "category": "T-Shirts"
  },
  {
    "image": "https://assets.myntassets.com/dpr_2,q_60,w_210,c_limit,fl_progressive/assets/images/1741358/2017/1/30/11485756395195-Wear-Your-Mind-Men-Tshirts-6251485756395023-1.jpg",
    "brand": "Wear Your Mind",
    "color": "Multy",
    "title": "Printed Round Neck T-shirt",
    "size": ["XS", "L", "XL", "3XL"],
    "sellingPrice": 384,
    "marketPrice": 1099,
    "percentageDiscount": 65,
    "faltDiscount": "",
    "inventory": 10,
    "collections": "Men",
    "subCollection": "Topwear",
    "gender": "Men",
    "category": "T-Shirts"
  },
  {
    "image": "https://assets.myntassets.com/dpr_2,q_60,w_210,c_limit,fl_progressive/assets/images/productimage/2021/2/25/1385f7ec-86e8-4e05-ac5e-4b1ebdaf7c081614263949131-1.jpg",
    "brand": "People",
    "color": "Multy",
    "title": "Solid Round Neck T-shirt",
    "size": ["S", "L", "XL", "2XL"],
    "sellingPrice": 279,
    "marketPrice": 399,
    "percentageDiscount": 30,
    "faltDiscount": "",
    "inventory": 10,
    "collections": "Men",
    "subCollection": "Topwear",
    "gender": "Men",
    "category": "T-Shirts"
  },
  {
    "image": "https://assets.myntassets.com/dpr_2,q_60,w_210,c_limit,fl_progressive/assets/images/10483014/2019/8/27/8a944aec-cc03-4cbd-8a54-e1fe6f4d9f181566898045210-VIMAL-JONNEY-Men-Multicoloured-Colourblocked-Round-Neck-T-sh-1.jpg",
    "brand": "VIMAL JONNEY",
    "color": "Multy",
    "title": "Men Pack of 2 T-shirts",
    "size": ["XS", "S", "M", "L"],
    "sellingPrice": 619,
    "marketPrice": 1998,
    "percentageDiscount": 69,
    "faltDiscount": "",
    "inventory": 10,
    "collections": "Men",
    "subCollection": "Topwear",
    "gender": "Men",
    "category": "T-Shirts"
  },
  {
    "image": "https://assets.myntassets.com/dpr_2,q_60,w_210,c_limit,fl_progressive/assets/images/productimage/2020/9/22/237ac803-b20d-42fd-b24a-daa348b077f11600731266731-1.jpg",
    "brand": "GESPO",
    "color": "Multy",
    "title": "Colourblocked Round Neck T-shirt",
    "size": ["XS", "M", "XL", "3XL"],
    "sellingPrice": 499,
    "marketPrice": 999,
    "percentageDiscount": 50,
    "faltDiscount": "",
    "inventory": 10,
    "collections": "Men",
    "subCollection": "Topwear",
    "gender": "Men",
    "category": "T-Shirts"
  },
  {
    "image": "https://assets.myntassets.com/dpr_2,q_60,w_210,c_limit,fl_progressive/assets/images/productimage/2020/12/16/0203cfdc-f01e-4b2a-850c-2dc6b98d38821608107112994-1.jpg",
    "brand": "MARCA Disati",
    "color": "Multy",
    "title": "Striped Round Neck T-shirt",
    "size": ["XS", "L", "XL", "3XL"],
    "sellingPrice": 359,
    "marketPrice": 899,
    "percentageDiscount": 60,
    "faltDiscount": "",
    "inventory": 10,
    "collections": "Men",
    "subCollection": "Topwear",
    "gender": "Men",
    "category": "T-Shirts"
  },
  {
    "image": "https://assets.myntassets.com/dpr_2,q_60,w_210,c_limit,fl_progressive/assets/images/productimage/2021/1/15/07ed4782-2ba6-4bf9-954f-24dab887423c1610715808080-1.jpg",
    "brand": "People",
    "color": "Multy",
    "title": "Striped Round Neck T-shirt",
    "size": ["S", "M", "L", "3XL"],
    "sellingPrice": 449,
    "marketPrice": 599,
    "percentageDiscount": 25,
    "faltDiscount": "",
    "inventory": 10,
    "collections": "Men",
    "subCollection": "Topwear",
    "gender": "Men",
    "category": "T-Shirts"
  },
  {
    "image": "https://assets.myntassets.com/dpr_2,q_60,w_210,c_limit,fl_progressive/assets/images/productimage/2021/2/25/12598a46-1719-43e7-ad7c-3f695cabd8b61614260193417-1.jpg",
    "brand": "People",
    "color": "Multy",
    "title": "Printed Round Neck T-shirt",
    "size": ["XS", "S", "M", "3XL"],
    "sellingPrice": 259,
    "marketPrice": 399,
    "percentageDiscount": 35,
    "faltDiscount": "",
    "inventory": 10,
    "collections": "Men",
    "subCollection": "Topwear",
    "gender": "Men",
    "category": "T-Shirts"
  },
  {
    "image": "https://assets.myntassets.com/dpr_2,q_60,w_210,c_limit,fl_progressive/assets/images/productimage/2021/3/9/5ba1357c-62d0-4487-aa47-445b208979a31615297619047-1.jpg",
    "brand": "Rodamo",
    "color": "Multy",
    "title": "Checked Polo Collar T-shirt",
    "size": ["S", "M", "L", "2XL"],
    "sellingPrice": 555,
    "marketPrice": 1049,
    "percentageDiscount": 47,
    "faltDiscount": "",
    "inventory": 10,
    "collections": "Men",
    "subCollection": "Topwear",
    "gender": "Men",
    "category": "T-Shirts"
  },
  {
    "image": "https://assets.myntassets.com/dpr_2,q_60,w_210,c_limit,fl_progressive/assets/images/productimage/2021/3/27/e2c7fe84-b526-4a5b-b537-2edad679fbf81616839537571-1.jpg",
    "brand": "UrGear",
    "color": "Multy",
    "title": "Striped Round Neck T-shirt",
    "size": ["S", "M", "XL", "3XL"],
    "sellingPrice": 0,
    "marketPrice": 0,
    "percentageDiscount": "",
    "faltDiscount": "",
    "inventory": 10,
    "collections": "Men",
    "subCollection": "Topwear",
    "gender": "Men",
    "category": "T-Shirts"
  },
  {
    "image": "https://assets.myntassets.com/dpr_2,q_60,w_210,c_limit,fl_progressive/assets/images/productimage/2021/3/25/b013ed69-517a-4a36-a73e-c86e2641dadd1616674686724-1.jpg",
    "brand": "UrGear",
    "color": "Multy",
    "title": "Striped Round Neck T-shirt",
    "size": ["XS", "S", "M", "3XL"],
    "sellingPrice": 619,
    "marketPrice": 1999,
    "percentageDiscount": 69,
    "faltDiscount": "",
    "inventory": 10,
    "collections": "Men",
    "subCollection": "Topwear",
    "gender": "Men",
    "category": "T-Shirts"
  },
  {
    "image": "https://assets.myntassets.com/dpr_2,q_60,w_210,c_limit,fl_progressive/assets/images/productimage/2021/3/27/2e29a705-0f02-4c99-bb3f-f6ad497e18bd1616834215184-1.jpg",
    "brand": "UrGear",
    "color": "Multy",
    "title": "Colourblocked Round Neck Pure Cotton T-shirt",
    "size": ["XS", "S", "XL", "3XL"],
    "sellingPrice": 626,
    "marketPrice": 1897,
    "percentageDiscount": 67,
    "faltDiscount": "",
    "inventory": 10,
    "collections": "Men",
    "subCollection": "Topwear",
    "gender": "Men",
    "category": "T-Shirts"
  },
  {
    "image": "https://assets.myntassets.com/dpr_2,q_60,w_210,c_limit,fl_progressive/assets/images/productimage/2021/5/6/d9cfaf41-5987-4a5b-927f-6112a4a039471620298190234-1.jpg",
    "brand": "Hangup",
    "color": "Multy",
    "title": "Printed Round Neck T-shirt",
    "size": ["XS", "M", "L", "3XL"],
    "sellingPrice": 374,
    "marketPrice": 1499,
    "percentageDiscount": 75,
    "faltDiscount": "",
    "inventory": 10,
    "collections": "Men",
    "subCollection": "Topwear",
    "gender": "Men",
    "category": "T-Shirts"
  },
  {
    "image": "https://assets.myntassets.com/dpr_2,q_60,w_210,c_limit,fl_progressive/assets/images/productimage/2021/5/6/da1a2806-b28c-4045-80bc-985b3a9757051620304738940-1.jpg",
    "brand": "Hangup",
    "color": "Multy",
    "title": "Floral Round Neck T-shirt",
    "size": ["S", "XL", "2XL", "3XL"],
    "sellingPrice": 374,
    "marketPrice": 1499,
    "percentageDiscount": 75,
    "faltDiscount": "",
    "inventory": 10,
    "collections": "Men",
    "subCollection": "Topwear",
    "gender": "Men",
    "category": "T-Shirts"
  },
  {
    "image": "https://assets.myntassets.com/dpr_2,q_60,w_210,c_limit,fl_progressive/assets/images/productimage/2021/5/6/555f6be3-be17-4b49-bcc3-b30eb1201af21620297910760-1.jpg",
    "brand": "hangup trend",
    "color": "Multy",
    "title": "Printed Round Neck Pure Cotton T-shirt",
    "size": ["S", "M", "2XL", "3XL"],
    "sellingPrice": 374,
    "marketPrice": 1499,
    "percentageDiscount": 75,
    "faltDiscount": "",
    "inventory": 10,
    "collections": "Men",
    "subCollection": "Topwear",
    "gender": "Men",
    "category": "T-Shirts"
  },
  {
    "image": "https://assets.myntassets.com/dpr_2,q_60,w_210,c_limit,fl_progressive/assets/images/productimage/2021/5/6/e46f4fb8-ed3d-4838-a791-70f7d51bb4e01620291761853-1.jpg",
    "brand": "hangup trend",
    "color": "Multy",
    "title": "Striped Henley Neck Pure Cotton T-shirt",
    "size": ["XS", "S", "M", "L"],
    "sellingPrice": 374,
    "marketPrice": 1499,
    "percentageDiscount": 75,
    "faltDiscount": "",
    "inventory": 10,
    "collections": "Men",
    "subCollection": "Topwear",
    "gender": "Men",
    "category": "T-Shirts"
  },
  {
    "image": "https://assets.myntassets.com/dpr_2,q_60,w_210,c_limit,fl_progressive/assets/images/productimage/2021/5/6/7a99e79b-996d-4dc4-bf67-723951b2ff561620304577488-1.jpg",
    "brand": "Hangup",
    "color": "Multy",
    "title": "Striped Henley Neck T-shirt",
    "size": ["S", "L", "XL", "2XL"],
    "sellingPrice": 374,
    "marketPrice": 1499,
    "percentageDiscount": 75,
    "faltDiscount": "",
    "inventory": 10,
    "collections": "Men",
    "subCollection": "Topwear",
    "gender": "Men",
    "category": "T-Shirts"
  },
  {
    "image": "https://assets.myntassets.com/dpr_2,q_60,w_210,c_limit,fl_progressive/assets/images/productimage/2021/5/8/f7c89e9e-783d-4d3c-8242-3a99c357d8141620447410793-1.jpg",
    "brand": "The Dry State",
    "color": "Multy",
    "title": "Colourblocked Round Neck T-shirt",
    "size": ["S", "L", "XL", "3XL"],
    "sellingPrice": 509,
    "marketPrice": 999,
    "percentageDiscount": 49,
    "faltDiscount": "",
    "inventory": 10,
    "collections": "Men",
    "subCollection": "Topwear",
    "gender": "Men",
    "category": "T-Shirts"
  },
  {
    "image": "https://assets.myntassets.com/dpr_2,q_60,w_210,c_limit,fl_progressive/assets/images/productimage/2021/5/8/bd77768e-fe13-4aae-a3eb-c540412a55be1620447526497-1.jpg",
    "brand": "UrGear",
    "color": "Multy",
    "title": "Dyed Round Neck Pure Cotton T-shirt",
    "size": ["XS", "S", "M", "XL"],
    "sellingPrice": 0,
    "marketPrice": 0,
    "percentageDiscount": "",
    "faltDiscount": "",
    "inventory": 10,
    "collections": "Men",
    "subCollection": "Topwear",
    "gender": "Men",
    "category": "T-Shirts"
  },
  {
    "image": "https://assets.myntassets.com/dpr_2,q_60,w_210,c_limit,fl_progressive/assets/images/productimage/2021/5/6/a2f0be36-ff66-41f6-8ac4-768058c285791620304185737-1.jpg",
    "brand": "hangup trend",
    "color": "Multy",
    "title": "Printed Round Neck T-shirt",
    "size": ["XS", "M", "XL", "3XL"],
    "sellingPrice": 374,
    "marketPrice": 1499,
    "percentageDiscount": 75,
    "faltDiscount": "",
    "inventory": 10,
    "collections": "Men",
    "subCollection": "Topwear",
    "gender": "Men",
    "category": "T-Shirts"
  },
  {
    "image": "https://assets.myntassets.com/dpr_2,q_60,w_210,c_limit,fl_progressive/assets/images/14413600/2021/9/21/f9f839cb-76cb-45d5-a79f-67455fe34f621632206353287-abof-Men-Tshirts-1811632206352684-1.jpg",
    "brand": "abof",
    "color": "Multy",
    "title": "Men Striped Polo Collar T-shirt",
    "size": ["XS", "M", "XL", "2XL"],
    "sellingPrice": 584,
    "marketPrice": 1299,
    "percentageDiscount": 55,
    "faltDiscount": "",
    "inventory": 10,
    "collections": "Men",
    "subCollection": "Topwear",
    "gender": "Men",
    "category": "T-Shirts"
  },
  {
    "image": "https://assets.myntassets.com/dpr_2,q_60,w_210,c_limit,fl_progressive/assets/images/productimage/2021/6/10/380cd4d1-17a3-4a81-807f-0477ce4493071623305305223-1.jpg",
    "brand": "AGIL ARMERO",
    "color": "Multy",
    "title": "Men Colourblocked T-shirt",
    "size": ["XS", "L", "XL", "2XL"],
    "sellingPrice": 0,
    "marketPrice": 0,
    "percentageDiscount": "",
    "faltDiscount": "",
    "inventory": 10,
    "collections": "Men",
    "subCollection": "Topwear",
    "gender": "Men",
    "category": "T-Shirts"
  },
  {
    "image": "https://assets.myntassets.com/dpr_2,q_60,w_210,c_limit,fl_progressive/assets/images/productimage/2021/6/19/0cdd56cc-679d-4e85-9af4-fd6122b212071624120508985-1.jpg",
    "brand": "Duke",
    "color": "Multy",
    "title": "Men Typography Printed Applique Slim Fit T-shirt",
    "size": ["M", "L", "2XL", "3XL"],
    "sellingPrice": 796,
    "marketPrice": 995,
    "percentageDiscount": 20,
    "faltDiscount": "",
    "inventory": 10,
    "collections": "Men",
    "subCollection": "Topwear",
    "gender": "Men",
    "category": "T-Shirts"
  },
  {
    "image": "https://assets.myntassets.com/dpr_2,q_60,w_210,c_limit,fl_progressive/assets/images/14797268/2021/8/3/21e1481d-ace6-46b2-a373-045c4c2461d41627985871638-Duke-Men-Multicoloured-Typography-Pack-of-3-Slim-Fit-T-shirt-1.jpg",
    "brand": "Duke",
    "color": "Multy",
    "title": "Men Slim Fit T-shirt",
    "size": ["XS", "S", "2XL", "3XL"],
    "sellingPrice": 756,
    "marketPrice": 945,
    "percentageDiscount": 20,
    "faltDiscount": "",
    "inventory": 10,
    "collections": "Men",
    "subCollection": "Topwear",
    "gender": "Men",
    "category": "T-Shirts"
  },
  {
    "image": "https://assets.myntassets.com/dpr_2,q_60,w_210,c_limit,fl_progressive/assets/images/14797264/2021/8/3/0920e65f-b4a7-484f-98f2-5520bd3260991627985854355-Duke-Men-Set-of-3-Typography-Printed-Slim-Fit-T-shirts-38516-1.jpg",
    "brand": "Duke",
    "color": "Multy",
    "title": "Men Set of 3 Printed T-shirts",
    "size": ["XS", "S", "2XL", "3XL"],
    "sellingPrice": 756,
    "marketPrice": 945,
    "percentageDiscount": 20,
    "faltDiscount": "",
    "inventory": 10,
    "collections": "Men",
    "subCollection": "Topwear",
    "gender": "Men",
    "category": "T-Shirts"
  },
  {
    "image": "https://assets.myntassets.com/dpr_2,q_60,w_210,c_limit,fl_progressive/assets/images/14845130/2021/8/18/0db92d42-dc8b-4ef9-ab81-9b5823f11c7d1629289808711TshirtsmezmodaMenTshirtsmezmodaMenTshirtsmezmodaMenTshirtsme1.jpg",
    "brand": "mezmoda",
    "color": "Multy",
    "title": "Men Printed Dry-Fit T-shirt",
    "size": ["XS", "M", "2XL", "3XL"],
    "sellingPrice": 544,
    "marketPrice": 1815,
    "percentageDiscount": 70,
    "faltDiscount": "",
    "inventory": 10,
    "collections": "Men",
    "subCollection": "Topwear",
    "gender": "Men",
    "category": "T-Shirts"
  },
  {
    "image": "https://assets.myntassets.com/dpr_2,q_60,w_210,c_limit,fl_progressive/assets/images/15162404/2021/8/17/7db18401-2eb7-4bcc-88ee-ce3bc0f1fb841629183276331Tshirts1.jpg",
    "brand": "Ennoble",
    "color": "Multy",
    "title": "Men Dyed Printed T-shirt",
    "size": ["M", "XL", "2XL", "3XL"],
    "sellingPrice": 1538,
    "marketPrice": 2699,
    "percentageDiscount": 43,
    "faltDiscount": "",
    "inventory": 10,
    "collections": "Men",
    "subCollection": "Topwear",
    "gender": "Men",
    "category": "T-Shirts"
  },
  {
    "image": "https://assets.myntassets.com/dpr_2,q_60,w_210,c_limit,fl_progressive/assets/images/15162454/2021/8/17/c27926fc-d7a3-408c-b7ce-efe0ec963cdc1629183273917Tshirts1.jpg",
    "brand": "Ennoble",
    "color": "Multy",
    "title": "Men Tie  Dye Pure Cotton T-shirt",
    "size": ["S", "M", "XL", "3XL"],
    "sellingPrice": 1538,
    "marketPrice": 2699,
    "percentageDiscount": 43,
    "faltDiscount": "",
    "inventory": 10,
    "collections": "Men",
    "subCollection": "Topwear",
    "gender": "Men",
    "category": "T-Shirts"
  },
  {
    "image": "https://assets.myntassets.com/dpr_2,q_60,w_210,c_limit,fl_progressive/assets/images/15494182/2021/9/28/386f26ec-63a5-4586-b525-c94156e1fa431632814178891GespoColorBlockMenRoundNeckMulticolorT-Shirt1.jpg",
    "brand": "GESPO",
    "color": "Multy",
    "title": "Men Colourblocked T-shirt",
    "size": ["L", "XL", "2XL", "3XL"],
    "sellingPrice": 491,
    "marketPrice": 1199,
    "percentageDiscount": 59,
    "faltDiscount": "",
    "inventory": 10,
    "collections": "Men",
    "subCollection": "Topwear",
    "gender": "Men",
    "category": "T-Shirts"
  },
  {
    "image": "https://assets.myntassets.com/dpr_2,q_60,w_210,c_limit,fl_progressive/assets/images/15494184/2021/9/28/77957d71-b233-4fbd-ac1a-d29690ac07eb1632814172402GespoColorblockMenRoundNeckMulticolorT-Shirt1.jpg",
    "brand": "GESPO",
    "color": "Multy",
    "title": "Cotton Colourblocked T-shirt",
    "size": ["M", "L", "2XL", "3XL"],
    "sellingPrice": 491,
    "marketPrice": 1199,
    "percentageDiscount": 59,
    "faltDiscount": "",
    "inventory": 10,
    "collections": "Men",
    "subCollection": "Topwear",
    "gender": "Men",
    "category": "T-Shirts"
  },
  {
    "image": "https://assets.myntassets.com/dpr_2,q_60,w_210,c_limit,fl_progressive/assets/images/15932500/2021/10/26/a50c0cbb-4a84-45de-8d93-3567974d73b21635253591549Tshirts1.jpg",
    "brand": "FERANOID",
    "color": "Multy",
    "title": "Men Pack Of 3 T-shirts",
    "size": ["XS", "M", "2XL", "3XL"],
    "sellingPrice": 1220,
    "marketPrice": 3299,
    "percentageDiscount": 63,
    "faltDiscount": "",
    "inventory": 10,
    "collections": "Men",
    "subCollection": "Topwear",
    "gender": "Men",
    "category": "T-Shirts"
  },
  {
    "image": "https://assets.myntassets.com/dpr_2,q_60,w_210,c_limit,fl_progressive/assets/images/15912698/2021/10/23/37cdaa74-a4a1-43d6-82a6-19be3e446f121634989160744PeopleMenMulticolouredColourblockedAppliqueT-shirt1.jpg",
    "brand": "People",
    "color": "Multy",
    "title": "Men Colourblocked T-shirt",
    "size": ["XS", "S", "XL", "2XL"],
    "sellingPrice": 349,
    "marketPrice": 499,
    "percentageDiscount": 30,
    "faltDiscount": "",
    "inventory": 10,
    "collections": "Men",
    "subCollection": "Topwear",
    "gender": "Men",
    "category": "T-Shirts"
  },
  {
    "image": "https://assets.myntassets.com/dpr_2,q_60,w_210,c_limit,fl_progressive/assets/images/15951516/2021/10/27/922ab99c-83b4-4b40-8322-73178405c4021635359356075UrGearMenMulticolouredStripedPoloCollarPocketsTrainingorGymT1.jpg",
    "brand": "UrGear",
    "color": "Multy",
    "title": "Men Striped Polo Collar Pockets T-shirt",
    "size": ["XS", "L", "XL", "2XL"],
    "sellingPrice": 647,
    "marketPrice": 2399,
    "percentageDiscount": 73,
    "faltDiscount": "",
    "inventory": 10,
    "collections": "Men",
    "subCollection": "Topwear",
    "gender": "Men",
    "category": "T-Shirts"
  },
  {
    "image": "https://assets.myntassets.com/dpr_2,q_60,w_210,c_limit,fl_progressive/assets/images/15957236/2021/10/28/e09356d0-9b52-44c5-87c4-f4d4b5a7e4991635415929181FERANOIDMenGreen3PocketsT-shirt1.jpg",
    "brand": "FERANOID",
    "color": "Multy",
    "title": "Men Pack Of 3 T-shirts",
    "size": ["XS", "M", "XL", "3XL"],
    "sellingPrice": 1469,
    "marketPrice": 4199,
    "percentageDiscount": 65,
    "faltDiscount": "",
    "inventory": 10,
    "collections": "Men",
    "subCollection": "Topwear",
    "gender": "Men",
    "category": "T-Shirts"
  },
  {
    "image": "https://assets.myntassets.com/dpr_2,q_60,w_210,c_limit,fl_progressive/assets/images/16023612/2021/11/6/c3eeb669-a4d4-45b4-b445-9afcbd97ce481636195059191AeropostaleMenMultiColourCrewNeckColourBlockT-Shirt1.jpg",
    "brand": "Aeropostale",
    "color": "Multy",
    "title": "Men Colourblocked T-shirt",
    "size": ["XS", "S", "XL", "3XL"],
    "sellingPrice": 799,
    "marketPrice": 1599,
    "percentageDiscount": 50,
    "faltDiscount": "",
    "inventory": 10,
    "collections": "Men",
    "subCollection": "Topwear",
    "gender": "Men",
    "category": "T-Shirts"
  }
]
